Workbook
Name CBNYM: SUMIF(CISS[SubGroup],'NY IS'!$A1,(INDIRECT("CISS[BNY"&'NY IS'!$B$4&"]")))
Name CBNYM: SUMIF(CISS[SubGroup],'TY IS'!$A1,(INDIRECT("CISS[BTY"&'TY IS'!$B$4&"]")))
Name CBNYM1: SUMPRODUCT((CISS[SubGroup]=YEAR!$A1)*(INDIRECT("CISS[["&YEAR!$M$6&"]:["&YEAR!$O$6&"]]")))
Name CBNYQ: SUMPRODUCT((CISS[SubGroup]='NY IS'!$A1)*(INDIRECT("CISS[[BNY"&RIGHT("0"&'NY IS'!$B$3,2)&"]:[BNY"&RIGHT("0"&'NY IS'!$B$4,2)&"]]")))
Name CBNYQ: SUMPRODUCT((CISS[SubGroup]='TY IS'!$A1)*(INDIRECT("CISS[[BTY"&RIGHT("0"&'TY IS'!$B$3,2)&"]:[BTY"&RIGHT("0"&'TY IS'!$B$4,2)&"]]")))
Name CBNYY: SUMPRODUCT((CISS[SubGroup]='NY IS'!$A1)*(INDIRECT("CISS[[BNY01]:[BNY"&RIGHT("0"&'NY IS'!$B$4,2)&"]]")))
Name CBNYY: SUMPRODUCT((CISS[SubGroup]='TY IS'!$A1)*(INDIRECT("CISS[[BTY01]:[BTY"&RIGHT("0"&'TY IS'!$B$4,2)&"]]")))
Name CNYM: SUMIF(CISS[SubGroup],'NY IS'!$A1,(INDIRECT("CISS[NY"&'NY IS'!$B$4&"]")))
Name CNYM: SUMIF(CISS[SubGroup],'TY IS'!$A1,(INDIRECT("CISS[TY"&'TY IS'!$B$4&"]")))
Name CNYM1: SUMPRODUCT((CISS[SubGroup]=YEAR!$A1)*(INDIRECT("CISS[["&YEAR!$M$5&"]:["&YEAR!$O$5&"]]")))
Name CNYQ: SUMPRODUCT((CISS[SubGroup]='NY IS'!$A1)*(INDIRECT("CISS[[NY"&RIGHT("0"&'NY IS'!$B$3,2)&"]:[NY"&RIGHT("0"&'NY IS'!$B$4,2)&"]]")))
Name CNYQ: SUMPRODUCT((CISS[SubGroup]='TY IS'!$A1)*(INDIRECT("CISS[[TY"&RIGHT("0"&'TY IS'!$B$3,2)&"]:[TY"&RIGHT("0"&'TY IS'!$B$4,2)&"]]")))
Name CNYY: SUMPRODUCT((CISS[SubGroup]='NY IS'!$A1)*(INDIRECT("CISS[[NY01]:[NY"&RIGHT("0"&'NY IS'!$B$4,2)&"]]")))
Name CNYY: SUMPRODUCT((CISS[SubGroup]='TY IS'!$A1)*(INDIRECT("CISS[[TY01]:[TY"&RIGHT("0"&'TY IS'!$B$4,2)&"]]")))
Name DBM: SUMIF(CSAS[ACCT],'NY IS'!$A1,(INDIRECT("CSAS[BNY"&'NY IS'!$B$4&"]")))
Name DBM: SUMIF(CSAS[ACCT],'TY IS'!$A1,(INDIRECT("CSAS[BTY"&'TY IS'!$B$4&"]")))
Name DBQ: SUMPRODUCT((CSAS[ACCT]='NY IS'!$A1)*(INDIRECT("CSAS[[BNY"&RIGHT("0"&'NY IS'!$B$3,2)&"]:[BNY"&RIGHT("0"&'NY IS'!$B$4,2)&"]]")))
Name DBQ: SUMPRODUCT((CSAS[ACCT]='TY IS'!$A1)*(INDIRECT("CSAS[[BTY"&RIGHT("0"&'TY IS'!$B$3,2)&"]:[BTY"&RIGHT("0"&'TY IS'!$B$4,2)&"]]")))
Name DBY: SUMPRODUCT((CSAS[ACCT]='NY IS'!$A1)*(INDIRECT("CSAS[[BNY01]:[BNY"&RIGHT("0"&'NY IS'!$B$4,2)&"]]")))
Name DBY: SUMPRODUCT((CSAS[ACCT]='TY IS'!$A1)*(INDIRECT("CSAS[[BTY01]:[BTY"&RIGHT("0"&'TY IS'!$B$4,2)&"]]")))
Name DM: SUMIF(CSAS[ACCT],'NY IS'!$A1,(INDIRECT("CSAS[NY"&'NY IS'!$B$4&"]")))
Name DM: SUMIF(CSAS[ACCT],'TY IS'!$A1,(INDIRECT("CSAS[TY"&'TY IS'!$B$4&"]")))
Name DM: SUMPRODUCT((CSAS[ACCT]=YEAR!$A22)*(INDIRECT("CSAS[["&YEAR!$M$5&"]:["&YEAR!$O$5&"]]")))
Name DMD: SUMPRODUCT((CSAS[ACCT]=YEAR!$A1)*(INDIRECT("CSAS[["&YEAR!$M$5&"]:["&YEAR!$O$5&"]]")))
Name DMMD: SUMPRODUCT((CSAS[ACCT]=YEAR!$A1)*(INDIRECT("CSAS[["&YEAR!$M$6&"]:["&YEAR!$O$6&"]]")))
Name DQ: SUMPRODUCT((CSAS[ACCT]='NY IS'!$A1)*(INDIRECT("CSAS[[NY"&RIGHT("0"&'NY IS'!$B$3,2)&"]:[NY"&RIGHT("0"&'NY IS'!$B$4,2)&"]]")))
Name DQ: SUMPRODUCT((CSAS[ACCT]='TY IS'!$A1)*(INDIRECT("CSAS[[TY"&RIGHT("0"&'TY IS'!$B$3,2)&"]:[TY"&RIGHT("0"&'TY IS'!$B$4,2)&"]]")))
Name DY: SUMPRODUCT((CSAS[ACCT]='NY IS'!$A1)*(INDIRECT("CSAS[[NY01]:[NY"&RIGHT("0"&'NY IS'!$B$4,2)&"]]")))
Name DY: SUMPRODUCT((CSAS[ACCT]='TY IS'!$A1)*(INDIRECT("CSAS[[TY01]:[TY"&RIGHT("0"&'TY IS'!$B$4,2)&"]]")))
Name LCDE: SUMPRODUCT((CSAS[ACCT_NO]=YEAR!$A1)*(INDIRECT("CSAS[["&YEAR!$M$5&"]:["&YEAR!$O$5&"]]")))
Name LCDESOBM: SUMIF(CSAS[ACCT_NO],'TY IS'!$A1,(INDIRECT("CSAS[BTY"&'TY IS'!$B$4&"]")))
Name LCDESOBM: SUMIF(CSAS[ACCT_NO],'NY IS'!$A1,(INDIRECT("CSAS[BNY"&'NY IS'!$B$4&"]")))
Name LCDESOBQ: SUMPRODUCT((CSAS[ACCT_NO]='TY IS'!$A1)*(INDIRECT("CSAS[[BTY"&RIGHT("0"&'TY IS'!$B$3,2)&"]:[BTY"&RIGHT("0"&'TY IS'!$B$4,2)&"]]")))
Name LCDESOBQ: SUMPRODUCT((CSAS[ACCT_NO]='NY IS'!$A1)*(INDIRECT("CSAS[[BNY"&RIGHT("0"&'NY IS'!$B$3,2)&"]:[BNY"&RIGHT("0"&'NY IS'!$B$4,2)&"]]")))
Name LCDESOBY: SUMPRODUCT((CSAS[ACCT_NO]='TY IS'!$A1)*(INDIRECT("CSAS[[BTY01]:[BTY"&RIGHT("0"&'TY IS'!$B$4,2)&"]]")))
Name LCDESOBY: SUMPRODUCT((CSAS[ACCT_NO]='NY IS'!$A1)*(INDIRECT("CSAS[[BNY01]:[BNY"&RIGHT("0"&'NY IS'!$B$4,2)&"]]")))
Name LCDESOM: SUMIF(CSAS[ACCT_NO],'TY IS'!$A1,(INDIRECT("CSAS[TY"&'TY IS'!$B$4&"]")))
Name LCDESOM: SUMIF(CSAS[ACCT_NO],'NY IS'!$A1,(INDIRECT("CSAS[NY"&'NY IS'!$B$4&"]")))
Name LCDESOQ: SUMPRODUCT((CSAS[ACCT_NO]='TY IS'!$A1)*(INDIRECT("CSAS[[TY"&RIGHT("0"&'TY IS'!$B$3,2)&"]:[TY"&RIGHT("0"&'TY IS'!$B$4,2)&"]]")))
Name LCDESOQ: SUMPRODUCT((CSAS[ACCT_NO]='NY IS'!$A1)*(INDIRECT("CSAS[[NY"&RIGHT("0"&'NY IS'!$B$3,2)&"]:[NY"&RIGHT("0"&'NY IS'!$B$4,2)&"]]")))
Name LCDESOY: SUMPRODUCT((CSAS[ACCT_NO]='TY IS'!$A1)*(INDIRECT("CSAS[[TY01]:[TY"&RIGHT("0"&'TY IS'!$B$4,2)&"]]")))
Name LCDESOY: SUMPRODUCT((CSAS[ACCT_NO]='NY IS'!$A1)*(INDIRECT("CSAS[[NY01]:[NY"&RIGHT("0"&'NY IS'!$B$4,2)&"]]")))
Name LSDM: SUMPRODUCT((CSAS[ACCT_NO]=YEAR!$A1)*(INDIRECT("CSAS[["&YEAR!$M$6&"]:["&YEAR!$O$6&"]]")))

Sheet YEAR
C1: CONSOLIDATED INCOME STATEMENT
C3: =IFERROR(VLOOKUP($D$4,REFERENCE!$A$2:$B$13,2,FALSE),0) -> 0 | E3: BEGIN YEAR: | F3: LAST YEAR | H3: END YEAR: | I3: THIS YEAR | L3: Begin | M3: =VLOOKUP(F3,REFERENCE!F2:G4,2,FALSE) -> LY | N3: End | O3: =VLOOKUP(I3,REFERENCE!F2:G4,2,FALSE) -> TY | P3: B
C4: =IFERROR(VLOOKUP($D$4,REFERENCE!$A$2:$B$13,2,FALSE),0) -> 0 | E4: BEGIN MONTH: | F4: JANUARY | H4: END MONTH: | I4: MARCH | M4: =VLOOKUP(F4,REFERENCE!A2:B13,2,FALSE) -> 10 | O4: =VLOOKUP(I4,REFERENCE!A2:B13,2,FALSE) -> 12
M5: =M3&M4 -> LY10 | O5: =O3&O4 -> TY12
M6: =P3&M5 -> BLY10 | O6: =P3&O5 -> BTY12
E7: ACTUAL | F7: BUDGET | G7: VARIANCE
A9: 104 | B9: Revenue | E9: =CNYM1 -> 16891319 | F9: =CBNYM1 -> 15715151 | G9: =+E9-F9 -> 1176168.5
A10: 106 | B10: Revenues: De Sousa (Toronto) | E10: =CNYM1 -> 528521.35 | F10: =CBNYM1 -> 541607.33 | G10: =+E10-F10 -> -13085.98
C11: REVENUE | E11: =E9+E10 -> 17419841 | F11: =F9+F10 -> 16256758 | G11: =+E11-F11 -> 1163082.5
E12: {=SUMPRODUCT((CISS[SubGroup]=YEAR!$A12)*(INDIRECT("CISS[["&YEAR!$M$6&"]:["&YEAR!$O$6&"]]")))} -> 0
C13: COGS
A14: 201 | B14: COGS: DEWS (HO) | E14: =CNYM1 -> 219471.53 | F14: =CBNYM1 -> 218420.96
A15: 204 | B15: COGS: Product | E15: =CNYM1 -> 8185198.4 | F15: =CBNYM1 -> 7823900.5
C16: Cost of Product | E16: =E14+E15 -> 8404669.9 | F16: =F14+F15 -> 8042321.4 | G16: =+E16-F16 -> 362348.48
A17: 700 | B17: COGS - Other | C17: Cost of Product - Other | E17: =CNYM1 -> 1564353 | F17: =CBNYM1 -> 494947.62 | G17: =+E17-F17 -> 1069405.4
A18: 444 | B18: Freight/Warehousing | C18: Freight and Warehousing | E18: =CNYM1 -> 207420.36 | F18: =CBNYM1 -> 160265.86 | G18: =+E18-F18 -> 47154.5
C19: Total COGS | E19: =SUM(E16:E18) -> 10176443 | F19: =SUM(F16:F18) -> 8697534.9 | G19: =SUM(G16:G18) -> 1478908.3
C20: Gross Margin | E20: =E11-E19 -> 7243397.6 | F20: =F11-F19 -> 7559223.4 | G20: =+E20-F20 -> -315825.86
C21: Gross Margin % | E21: =E20/E11 -> 0.41581307 | F21: =F20/F11 -> 0.46498959
C23: EXPENSE
C24: Personnel costs
A25: 409 | B25: SG&A: Employee Benefits | C25: Employee Comp & benefits | E25: =CNYM1 -> 1469246.8 | F25: =CBNYM1 -> 1481917.8 | G25: =+E25-F25 -> -12670.98
A26: 404 | B26: SG&A: Automotive | C26: Automobile | E26: =CNYM1 -> 93554.34 | F26: =CBNYM1 -> 84207.47 | G26: =+E26-F26 -> 9346.87
C27: Share Based payments
C28: Total Personnel Costs | E28: =SUM(E25:E27) -> 1562801.2 | F28: =SUM(F25:F27) -> 1566125.3 | G28: =+E28-F28 -> -3324.11
C30: Sales & Marketing
A31: 407 | B31: SG&A: Commissions | C31: Commissions | E31: =CNYM1 -> 1101762.8 | F31: =CBNYM1 -> 1165903.4 | G31: =+E31-F31 -> -64140.64
A32: 401 | B32: SG&A: Advertising | C32: Advertising & Promotions | E32: =CNYM1 -> 2084109.3 | F32: =CBNYM1 -> 1849424.1 | G32: =+E32-F32 -> 234685.14
A33: 71550 | B33: SG&A: Advertising | C33: Donations | E33: =DMD -> 71988.76 | F33: =DMMD -> 48097 | G33: =+E33-F33 -> 23891.76
A34: 440 | B34: Royalties | C34: Royalties | E34: =CNYM1 -> 138676.81 | F34: =CBNYM1 -> 141088.83 | G34: =+E34-F34 -> -2412.02
C35: Total Sales & Marketing | E35: =SUM(E31:E34) -> 3396537.6 | F35: =SUM(F31:F34) -> 3204513.4 | G35: =+E35-F35 -> 192024.24
C37: G&A
A38: 405 | B38: SG&A: Bad Debts | C38: Bad Debts | E38: =CNYM1 -> 39595.85 | F38: =CBNYM1 -> 2400 | G38: =+E38-F38 -> 37195.85
A39: 412 | B39: SG&A: Insurance | C39: Insurance | E39: =CNYM1 -> 35406.52 | F39: =CBNYM1 -> 24903.09 | G39: =+E39-F39 -> 10503.43
A40: 415 | B40: SG&A: Management Fees | C40: Management Fees | E40: =CNYM1 -> 187488 | F40: =CBNYM1 -> 0 | G40: =+E40-F40 -> 187488
A41: 416 | B41: SG&A: Occupancy Costs | C41: Occupancy costs | E41: =CNYM1 -> 141038.69 | F41: =CBNYM1 -> 136944.99 | G41: =+E41-F41 -> 4093.7
A42: EXE71470 | B42: SG&A: Occupancy Costs | C42: Lease Costs - Beamsville | E42: =-LCDE -> -77773.8 | F42: =LSDM -> 74577 | G42: =+E42-F42 -> -152350.8
A43: 417 | B43: SG&A: Office & General | C43: Office and General | E43: =CNYM1 -> 218707.16 | F43: =CBNYM1 -> 188096.63 | G43: =+E43-F43 -> 30610.53
A44: 418 | B44: SG&A: Professional Fees | C44: Professional Fees | E44: =CNYM1 -> 285504 | F44: =CBNYM1 -> 279932.56 | G44: =+E44-F44 -> 5571.44
A45: 421 | B45: SG&A: Repairs/Maintenance | C45: R&M | E45: =CNYM1 -> 110941.79 | F45: =CBNYM1 -> 71214.32 | G45: =+E45-F45 -> 39727.47
A46: 426 | B46: SG&A: Telephone | C46: Telephone | E46: =CNYM1 -> 52590.55 | F46: =CBNYM1 -> 37573.44 | G46: =+E46-F46 -> 15017.11
A47: 428 | B47: SG&A: Utilities | C47: Utilities | E47: =CNYM1 -> 26271.56 | F47: =CBNYM1 -> 23696.68 | G47: =+E47-F47 -> 2574.88
A48: 445 | B48: Membership/Dues/Licenses | C48: Memberships/dues/licenses | E48: =CNYM1 -> 2349.43 | F48: =CBNYM1 -> 3159.96 | G48: =+E48-F48 -> -810.53
A49: 805 | B49: Reorganization costs | C49: Re-organization costs | E49: =CNYM1 -> 0 | F49: =CBNYM1 -> 0 | G49: =+E49-F49 -> 0
A50: 899 | B50: Other expenses | C50: Other expenses | E50: =CNYM1 -> 0 | F50: =CBNYM1 -> 0 | G50: =+E50-F50 -> 0
A51: 901 | B51: Other Expenses | C51: Other expenses | E51: =CNYM1 -> 0 | F51: =CBNYM1 -> 0 | G51: =+E51-F51 -> 0
C52: Total G&A | E52: =SUM(E38:E51) -> 1022119.8 | F52: =SUM(F38:F51) -> 842498.67 | G52: =+E52-F52 -> 179621.08
E53: =CNYM1 -> 0 | F53: =CBNYM1 -> 0 | G53: =+E53-F53 -> 0
C54: TOTAL EXPENSES | E54: =E28+E35+E52 -> 5981458.5 | F54: =F28+F35+F52 -> 5613137.3 | G54: =+E54-F54 -> 368321.21
C56: EBITDA | E56: =E20-E54 -> 1261939 | F56: =F20-F54 -> 1946086.1 | G56: =+E56-F56 -> -684147.07
C57: EBITDA % | E57: =E56/E11 -> 0.072442626 | F57: =F56/F11 -> 0.11970936 | G57: =+E57-F57 -> -0.047266731
A59: 711 | B59: Interest - LTD | C59: Interest on bank indebtedness | E59: =CNYM1 -> 1401980.4 | F59: =CBNYM1 -> 1171174.1 | G59: =+E59-F59 -> 230806.29
A60: 446 | B60: Financing Fees | C60: Financing Costs | E60: =CNYM1 -> 1807.37 | F60: =CBNYM1 -> 180000 | G60: =+E60-F60 -> -178192.63
A61: 701 | B61: Depreciation - Capital Assets | C61: Depreciation of PP&E | E61: =CNYM1 -> 1105926.4 | F61: =CBNYM1 -> 900535.91 | G61: =+E61-F61 -> 205390.52
A62: 702 | B62: Amortization - Intangibles | C62: Amortization of Intangible Assets | E62: =CNYM1 -> 1564.24 | F62: =CBNYM1 -> 809.8 | G62: =+E62-F62 -> 754.44
C64: Extraordinary
C65: Loss from Operations | E65: =CNYM1 -> 0 | F65: =CBNYM1 -> 0 | G65: =+E65-F65 -> 0
A66: 740 | B66: Gain/Loss on Sale of Assets | C66: Loss on disposal - assets held for sale | E66: =CNYM1 -> 0 | F66: =CBNYM1 -> 0 | G66: =+E66-F66 -> 0
C67: Restructuring charges | E67: =CNYM1 -> 0 | F67: =CBNYM1 -> 0 | G67: =+E67-F67 -> 0
E68: =CNYM1 -> 0 | F68: =CBNYM1 -> 0 | G68: =+E68-F68 -> 0
C69: Net Income/Loss | E69: =E56-E59-E60-E61-E62-E65-E66-E67 -> -1249339.4 | F69: =F56-F59-F60-F61-F62-F65-F66-F67 -> -306433.74 | G69: =+E69-F69 -> -942905.69
A97: CBNYM | B97: SUMIF(CISS[SubGroup],'LY IS'!$A97,(INDIRECT("CISS[BLY"&'LY IS'!$B$4&"]")))

Sheet TY IS
C1: EDPYPF CONSOLIDATED INCOME STATEMENT
B3: =IFERROR(VLOOKUP($D$3,REFERENCE!$J$2:$M$3,3,FALSE),0) -> LY10 | C3: BEGIN YEAR: | D3: LAST YEAR
B4: =IFERROR(VLOOKUP($D$4,REFERENCE!$A$2:$B$13,2,FALSE),0) -> 12 | C4: BEGIN MONTH: | D4: MARCH
C6: =CNYM -> 0
D7: ACTUAL | E7: BUDGET | F7: VAR | G7: QTD | H7: BQTD | I7: VAR | J7: YTD | K7: BYTD | L7: VAR | N7: NC | O7: DS | P7: HO | Q7: DSTO | R7: Total BV | S7: RL | T7: VAR | V7: NC | W7: DS | X7: HO | Y7: DSTO | Z7: Total BV | AA7: RL | AB7: VAR
AE8: NC | AF8: HO | AG8: DS | AH8: DST | AI8: Total
A9: 104 | B9: Revenue | D9: =CNYM -> 998987.72 | E9: =CBNYM -> 1222999.1 | F9: =+D9-E9 -> -224011.43 | G9: {=SUMPRODUCT((CISS[SubGroup]=$A9)*(INDIRECT("CISS[[TY"&RIGHT("0"&$B$3,2)&"]:[TY"&RIGHT("0"&$B$4,2)&"]]")))} -> 2707697.8 | H9: =CBNYQ -> 2771727.1 | J9: {=SUMPRODUCT((CISS[SubGroup]=$A9)*(INDIRECT("CISS[[TY01]:[TY"&RIGHT("0"&$B$4,2)&"]]")))} -> 14042003 | K9: =CBNYY -> 15715151
A10: 106 | B10: Revenues: De Sousa (Toronto) | D10: =CNYM -> 34602.1 | E10: =CBNYM -> 31928.64 | F10: =+D10-E10 -> 2673.46 | G10: =CNYQ -> 96099.2 | H10: =CBNYQ -> 83010.48 | J10: =CNYY -> 448362.06 | K10: =CBNYY -> 432945.05
C11: REVENUE | D11: =SUM(D9:D10) -> 1033589.8 | E11: =SUM(E9:E10) -> 1254927.8 | F11: =+D11-E11 -> -221337.97 | G11: =SUM(G9:G10) -> 2803797 | H11: =SUM(H9:H10) -> 2854737.6 | I11: =+G11-H11 -> -50940.62 | J11: =SUM(J9:J10) -> 14490365 | K11: =SUM(K9:K10) -> 16148096 | L11: =+J11-K11 -> -1657731.5 | N11: 699065.43 | O11: 9347.08 | Q11: 31573.44 | R11: =SUM(N11:Q11) -> 739985.95 | S11: =+D11 -> 1033589.8 | T11: =+R11-S11 -> -293603.87 | V11: 13826311 | W11: 207251.28 | Y11: 413759.96 | Z11: =SUM(V11:Y11) -> 14447323 | AA11: =+J11 -> 14490365 | AB11: =+Z11-AA11 -> -43041.97 | AD11: Total Gross Sales | AE11: 13826311 | AF11: 0 | AG11: 213178.06 | AH11: 452945.51 | AI11: =IF(AE11<>"",SUM(AE11:AH11),"") -> 14492435
AI12: =IF(AE12<>"",SUM(AE12:AH12),"")
C13: COGS
A14: 201 | B14: COGS: DEWS (HO) | D14: =CNYM -> 14000.95 | E14: =CBNYM -> 15039.43 | G14: =CNYQ -> 38929.61 | H14: =CBNYQ -> 37360.46 | J14: =CNYY -> 184406.21 | K14: =CBNYY -> 176860.5 | AI14: =IF(AE14<>"",SUM(AE14:AH14),"")
A15: 204 | B15: COGS: Product | D15: =CNYM -> 531731.16 | E15: =CBNYM -> 524192.19 | G15: =CNYQ -> 1219283.4 | H15: =CBNYQ -> 1305538.1 | J15: =CNYY -> 6741300.6 | K15: =CBNYY -> 7823900.5 | AD15: Cost of Goods Sold | AI15: =IF(AE15<>"",SUM(AE15:AH15),"")
C16: Cost of Product | D16: =SUM(D14:D15) -> 545732.11 | E16: =SUM(E14:E15) -> 539231.62 | F16: =+D16-E16 -> 6500.49 | G16: =SUM(G14:G15) -> 1258213 | H16: =SUM(H14:H15) -> 1342898.6 | I16: =+G16-H16 -> -84685.53 | J16: =SUM(J14:J15) -> 6925706.8 | K16: =SUM(K14:K15) -> 8000761 | L16: =+J16-K16 -> -1075054.2 | N16: 297951.5 | O16: 3347.01 | Q16: 12520.03 | R16: =SUM(N16:Q16) -> 313818.54 | S16: =+D16 -> 545732.11 | T16: =+R16-S16 -> -231913.57 | V16: 6607537.1 | W16: 48896.09 | Y16: 170405.26 | Z16: =SUM(V16:Y16) -> 6826838.5 | AA16: =+J16 -> 6925706.8 | AB16: =+Z16-AA16 -> -98868.32 | AD16: COGS: Product | AE16: 6607537.1 | AF16: 0 | AG16: 57928.65 | AH16: 184406.21 | AI16: =IF(AE16<>"",SUM(AE16:AH16),"") -> 6849872
A17: 700 | B17: COGS - Other | C17: Cost of Product - Other | D17: =CNYM -> 337005.35 | E17: =CBNYM -> 250395.83 | F17: =+D17-E17 -> 86609.52 | G17: =CNYQ -> 594152.87 | H17: =CBNYQ -> 271187.49 | I17: =+G17-H17 -> 322965.38 | J17: =CNYY -> 1278484.4 | K17: =CBNYY -> 494947.62 | L17: =+J17-K17 -> 783536.76 | N17: 81979.87 | R17: =SUM(N17:Q17) -> 81979.87 | S17: =+D17 -> 337005.35 | T17: =+R17-S17 -> -255025.48 | V17: 982243.81 | W17: 56391 | Z17: =SUM(V17:Y17) -> 1038634.8 | AA17: =+J17 -> 1278484.4 | AB17: =+Z17-AA17 -> -239849.57 | AD17: Royalties | AE17: 110145.18 | AF17: 0 | AG17: 0 | AH17: 3336.04 | AI17: =IF(AE17<>"",SUM(AE17:AH17),"") -> 113481.22
A18: 444 | B18: Freight/Warehousing | C18: Freight and Warehousing | D18: =CNYM -> 20778.14 | E18: =CBNYM -> 13150.32 | F18: =+D18-E18 -> 7627.82 | G18: =CNYQ -> 51355.1 | H18: =CBNYQ -> 39054.3 | I18: =+G18-H18 -> 12300.8 | J18: =CNYY -> 171474.4 | K18: =CBNYY -> 157265.86 | L18: =+J18-K18 -> 14208.54 | N18: 11561.99 | O18: 1016.06 | Q18: 1000 | R18: =SUM(N18:Q18) -> 13578.05 | S18: =+D18 -> 20778.14 | T18: =+R18-S18 -> -7200.09 | V18: 18743.02 | W18: 11574.24 | Y18: 11000 | Z18: =SUM(V18:Y18) -> 41317.26 | AA18: =+J18 -> 171474.4 | AB18: =+Z18-AA18 -> -130157.14 | AD18: COGS - Other | AE18: 982243.81 | AF18: 0 | AG18: 56391 | AH18: 0 | AI18: =IF(AE18<>"",SUM(AE18:AH18),"") -> 1038634.8
C19: Total COGS | D19: =SUM(D16:D18) -> 903515.6 | E19: =SUM(E16:E18) -> 802777.77 | F19: =SUM(F16:F18) -> 100737.83 | G19: =SUM(G16:G18) -> 1903721 | H19: =SUM(H16:H18) -> 1653140.4 | I19: =SUM(I16:I18) -> 250580.65 | J19: =SUM(J16:J18) -> 8375665.6 | K19: =SUM(K16:K18) -> 8652974.4 | L19: =SUM(L16:L18) -> -277308.86 | AD19: Total Cost of Goods Sold | AE19: 7699926.1 | AF19: 0 | AG19: 114319.65 | AH19: 187742.25 | AI19: =IF(AE19<>"",SUM(AE19:AH19),"") -> 8001988
C20: Gross Margin | D20: =D11-D19 -> 130074.22 | E20: =E11-E19 -> 452150.02 | F20: =+D20-E20 -> -322075.8 | G20: =G11-G19 -> 900076 | H20: =H11-H19 -> 1201597.3 | I20: =+G20-H20 -> -301521.27 | J20: =J11-J19 -> 6114699 | K20: =K11-K19 -> 7495121.6 | L20: =+J20-K20 -> -1380422.6 | AD20: GROSS PROFIT | AE20: 6126385.2 | AF20: 0 | AG20: 98858.41 | AH20: 265203.26 | AI20: =AI11-AI19 -> 6490446.9
C21: Gross Margin % | D21: =D20/D11 -> 0.12584704 | E21: =E20/E11 -> 0.36029963 | G21: =G20/G11 -> 0.32102039 | H21: =H20/H11 -> 0.42091338 | J21: =J20/J11 -> 0.42198379 | K21: =K20/K11 -> 0.46414894 | AI21: =IF(AE21<>"",SUM(AE21:AH21),"")
AD22: Operating Expense | AI22: =IF(AE22<>"",SUM(AE22:AH22),"")
C23: EXPENSE | AD23: SG&A: Advertising | AE23: 1742076.8 | AF23: 8079.23 | AG23: 18298.5 | AH23: 19914.22 | AI23: =IF(AE23<>"",SUM(AE23:AH23),"") -> 1788368.8
C24: Personnel costs | AD24: SG&A: Commissions | AE24: 916383.25 | AF24: 0 | AG24: 8355.04 | AH24: 1011.99 | AI24: =IF(AE24<>"",SUM(AE24:AH24),"") -> 925750.28
A25: 409 | B25: SG&A: Employee Benefits | C25: Employee Comp & benefits | D25: =CNYM -> 109502.81 | E25: =CBNYM -> 123277.31 | F25: =+D25-E25 -> -13774.5 | G25: =CNYQ -> 336998.16 | H25: =CBNYQ -> 351478.87 | I25: =+G25-H25 -> -14480.71 | J25: =CNYY -> 1386711.2 | K25: =CBNYY -> 1457798.2 | L25: =+J25-K25 -> -71086.95 | N25: 51606 | O25: 2403.16 | P25: 37429.5 | Q25: 7413.93 | R25: =SUM(N25:Q25) -> 98852.59 | S25: =+D25 -> 109502.81 | T25: =+R25-S25 -> -10650.22 | V25: 62133.8 | W25: 40312.87 | X25: 553903.88 | Y25: 86480.56 | Z25: =SUM(V25:Y25) -> 742831.11 | AA25: =+J25 -> 1386711.2 | AB25: =+Z25-AA25 -> -643880.09 | AD25: SG&A: Employee Benefits | AE25: 658644.88 | AF25: 614795.22 | AG25: 43102.23 | AH25: 94453 | AI25: =IF(AE25<>"",SUM(AE25:AH25),"") -> 1410995.3
A26: 404 | B26: SG&A: Automotive | C26: Automobile | D26: =CNYM -> 7455.07 | E26: =CBNYM -> 7801.68 | F26: =+D26-E26 -> -346.61 | G26: =CNYQ -> 22926.65 | H26: =CBNYQ -> 22240.23 | I26: =+G26-H26 -> 686.42 | J26: =CNYY -> 93554.34 | K26: =CBNYY -> 84207.47 | L26: =+J26-K26 -> 9346.87 | N26: 6399.45 | P26: 1008.31 | Q26: 39.7 | R26: =SUM(N26:Q26) -> 7447.46 | S26: =+D26 -> 7455.07 | T26: =+R26-S26 -> -7.61 | V26: 6774.36 | X26: 11360.88 | Y26: 39.7 | Z26: =SUM(V26:Y26) -> 18174.94 | AA26: =+J26 -> 93554.34 | AB26: =+Z26-AA26 -> -75379.4 | AD26: Freight/Warehousing | AE26: 146865.04 | AF26: 0 | AG26: 12609.36 | AH26: 12000 | AI26: =IF(AE26<>"",SUM(AE26:AH26),"") -> 171474.4
C27: Share Based payments | D27: =CNYM -> 0 | E27: =CBNYM -> 0 | G27: =CNYQ -> 0 | H27: =CBNYQ -> 0 | J27: =CNYY -> 0 | K27: =CBNYY -> 0 | R27: =SUM(N27:Q27) -> 0 | S27: =+D27 -> 0 | T27: =+R27-S27 -> 0 | AD27: Total Operating Expense | AE27: 3464395 | AF27: 622874.45 | AG27: 82365.13 | AH27: 127379.21 | AI27: =IF(AE27<>"",SUM(AE27:AH27),"") -> 4297013.8
C28: Total Personnel Costs | D28: =SUM(D25:D27) -> 116957.88 | E28: =SUM(E25:E27) -> 131078.99 | F28: =+D28-E28 -> -14121.11 | G28: =SUM(G25:G27) -> 359924.81 | H28: =SUM(H25:H27) -> 373719.1 | I28: =+G28-H28 -> -13794.29 | J28: =SUM(J25:J27) -> 1480265.5 | K28: =SUM(K25:K27) -> 1542005.6 | L28: =+J28-K28 -> -61740.08 | AD28: OPERATING INCOME (LOSS) | AE28: 2661990.3 | AF28: -622874.45 | AG28: 16493.28 | AH28: 137824.05 | AI28: =AI20-AI27 -> 2193433.2
AI29: =IF(AE29<>"",SUM(AE29:AH29),"")
C30: Sales & Marketing | AD30: General & Admin Expense | AI30: =IF(AE30<>"",SUM(AE30:AH30),"")
A31: 407 | B31: SG&A: Commissions | C31: Commissions | D31: =CNYM -> 68157.54 | E31: =CBNYM -> 70019.9 | F31: =+D31-E31 -> -1862.36 | G31: =CNYQ -> 212704.78 | H31: =CBNYQ -> 202880.55 | I31: =+G31-H31 -> 9824.23 | J31: =CNYY -> 929986.5 | K31: =CBNYY -> 1165903.4 | L31: =+J31-K31 -> -235916.93 | N31: 66364.53 | O31: 452.65 | Q31: 61.49 | R31: =SUM(N31:Q31) -> 66878.67 | S31: =+D31 -> 68157.54 | T31: =+R31-S31 -> -1278.87 | V31: 60825.59 | W31: 7974.65 | Y31: 987.27 | Z31: =SUM(V31:Y31) -> 69787.51 | AA31: =+J31 -> 929986.5 | AB31: =+Z31-AA31 -> -860198.99 | AD31: SG&A: Automotive | AE31: 81473.05 | AF31: 12041.59 | AG31: 0 | AH31: 39.7 | AI31: =IF(AE31<>"",SUM(AE31:AH31),"") -> 93554.34
A32: 401 | B32: SG&A: Advertising | C32: Advertising & Promotions | D32: =CNYM-D33 -> 28626.58 | E32: =CBNYM-E33 -> 116366.63 | F32: =+D32-E32 -> -87740.05 | G32: =CNYQ-G33 -> 314292.23 | H32: =CBNYQ-H33 -> 283442.47 | I32: =+G32-H32 -> 30849.76 | J32: =CNYY-J33 -> 1735557.3 | K32: =CBNYY-K33 -> 1797584.2 | L32: =+J32-K32 -> -62026.88 | N32: 175458.51 | O32: 1350.53 | P32: 645.62 | Q32: 839.25 | R32: =SUM(N32:Q32) -> 178293.91 | S32: =+D32 -> 28626.58 | T32: =+R32-S32 -> 149667.33 | V32: 1689251.7 | W32: 17507.01 | X32: 7592.81 | Y32: 14337.56 | Z32: =SUM(V32:Y32) -> 1728689 | AA32: =+J32 -> 1735557.3 | AB32: =+Z32-AA32 -> -6868.3 | AD32: SG&A: Bad Debts | AE32: 15021.31 | AF32: 0 | AG32: 1224.15 | AH32: 351 | AI32: =IF(AE32<>"",SUM(AE32:AH32),"") -> 16596.46
A33: 71550 | B33: SG&A: Advertising | C33: Donations | D33: =DM -> 376.38 | E33: =DBM -> 3185 | F33: =+D33-E33 -> -2808.62 | G33: =DQ -> -1787.14 | H33: =DBQ -> 6837 | I33: =+G33-H33 -> -8624.14 | J33: =DY -> 22134.66 | K33: =DBY -> 48097 | L33: =+J33-K33 -> -25962.34 | R33: =SUM(N33:Q33) -> 0 | S33: =+D33 -> 376.38 | T33: =+R33-S33 -> -376.38 | Z33: =SUM(V33:Y33) -> 0 | AA33: =+J33 -> 22134.66 | AB33: =+Z33-AA33 -> -22134.66 | AD33: SG&A: Insurance | AE33: 8655 | AF33: 22660.79 | AG33: 354.35 | AH33: 394.4 | AI33: =IF(AE33<>"",SUM(AE33:AH33),"") -> 32064.54
A34: 440 | B34: Royalties | C34: Royalties | D34: =CNYM -> 6435.37 | E34: =CBNYM -> 6683.96 | F34: =+D34-E34 -> -248.59 | G34: =CNYQ -> 24439.98 | H34: =CBNYQ -> 20295.18 | I34: =+G34-H34 -> 4144.8 | J34: =CNYY -> 113481.22 | K34: =CBNYY -> 140646.28 | L34: =+J34-K34 -> -27165.06 | N34: 6003.77 | Q34: 171.97 | R34: =SUM(N34:Q34) -> 6175.74 | S34: =+D34 -> 6435.37 | T34: =+R34-S34 -> -259.63 | V34: 104046.76 | Y34: 2999.09 | Z34: =SUM(V34:Y34) -> 107045.85 | AA34: =+J34 -> 113481.22 | AB34: =+Z34-AA34 -> -6435.37 | AD34: SG&A: Management Fees | AE34: 0 | AF34: 0 | AG34: 0 | AH34: 0 | AI34: =IF(AE34<>"",SUM(AE34:AH34),"") -> 0
C35: Total Sales & Marketing | D35: =SUM(D31:D34) -> 103595.87 | E35: =SUM(E31:E34) -> 196255.49 | F35: =+D35-E35 -> -92659.62 | G35: =SUM(G31:G34) -> 549649.85 | H35: =SUM(H31:H34) -> 513455.2 | I35: =+G35-H35 -> 36194.65 | J35: =SUM(J31:J34) -> 2801159.7 | K35: =SUM(K31:K34) -> 3152230.9 | L35: =+J35-K35 -> -351071.21 | AD35: SG&A: Occupancy Costs | AE35: 0 | AF35: 1190.95 | AG35: 77773.8 | AH35: 49538.77 | AI35: =IF(AE35<>"",SUM(AE35:AH35),"") -> 128503.52
E36: =CBNYM -> 0 | AD36: SG&A: Office & General | AE36: 78250.97 | AF36: 105232.79 | AG36: 3163.5 | AH36: 8581.63 | AI36: =IF(AE36<>"",SUM(AE36:AH36),"") -> 195228.89
C37: G&A | E37: =CBNYM -> 0 | AD37: SG&A: Professional Fees | AE37: 5175 | AF37: 284316.52 | AG37: 0 | AH37: -412.5 | AI37: =IF(AE37<>"",SUM(AE37:AH37),"") -> 289079.02
A38: 405 | B38: SG&A: Bad Debts | C38: Bad Debts | D38: =CNYM -> 60423.04 | E38: =CBNYM -> 200 | F38: =+D38-E38 -> 60223.04 | G38: =CNYQ -> 60423.04 | H38: =CBNYQ -> 600 | I38: =+G38-H38 -> 59823.04 | J38: =CNYY -> 68229.49 | K38: =CBNYY -> 2400 | L38: =+J38-K38 -> 65829.49 | R38: =SUM(N38:Q38) -> 0 | S38: =+D38 -> 60423.04 | T38: =+R38-S38 -> -60423.04 | V38: 7593.9 | W38: 212.55 | Z38: =SUM(V38:Y38) -> 7806.45 | AA38: =+J38 -> 68229.49 | AB38: =+Z38-AA38 -> -60423.04 | AD38: SG&A: Repairs/Maintenance | AE38: 88201.32 | AF38: 0 | AG38: 12135.56 | AH38: 4005.51 | AI38: =IF(AE38<>"",SUM(AE38:AH38),"") -> 104342.39
A39: 412 | B39: SG&A: Insurance | C39: Insurance | D39: =CNYM -> 4114.99 | E39: =CBNYM -> 2069 | F39: =+D39-E39 -> 2045.99 | G39: =CNYQ -> 12344.97 | H39: =CBNYQ -> 6207 | I39: =+G39-H39 -> 6137.97 | J39: =CNYY -> 34298.71 | K39: =CBNYY -> 24828 | L39: =+J39-K39 -> 9470.71 | N39: 1731 | P39: 2292.88 | R39: =SUM(N39:Q39) -> 4023.88 | S39: =+D39 -> 4114.99 | T39: =+R39-S39 -> -91.11 | V39: 6924 | W39: 317.91 | X39: 22602.08 | Y39: 339.73 | Z39: =SUM(V39:Y39) -> 30183.72 | AA39: =+J39 -> 34298.71 | AB39: =+Z39-AA39 -> -4114.99 | AD39: SG&A: Telephone | AE39: 24245.12 | AF39: 10259.27 | AG39: 10853.54 | AH39: 2305.85 | AI39: =IF(AE39<>"",SUM(AE39:AH39),"") -> 47663.78
A40: 415 | B40: SG&A: Management Fees | C40: Management Fees | D40: =CNYM -> 0 | E40: =CBNYM -> 0 | F40: =+D40-E40 -> 0 | G40: =CNYQ -> 0 | H40: =CBNYQ -> 0 | I40: =+G40-H40 -> 0 | J40: =CNYY -> 0 | K40: =CBNYY -> 0 | L40: =+J40-K40 -> 0 | R40: =SUM(N40:Q40) -> 0 | S40: =+D40 -> 0 | T40: =+R40-S40 -> 0 | Z40: =SUM(V40:Y40) -> 0 | AA40: =+J40 -> 0 | AB40: =+Z40-AA40 -> 0 | AD40: SG&A: Utilities | AE40: 6881.26 | AF40: 0 | AG40: 10853.54 | AH40: 6848.62 | AI40: =IF(AE40<>"",SUM(AE40:AH40),"") -> 24583.42
A41: 416 | B41: SG&A: Occupancy Costs | C41: Occupancy costs | D41: =CNYM-D42 -> 4127.33 | E41: =CBNYM-E42 -> 4179 | F41: =+D41-E41 -> -51.67 | G41: =CNYQ-G42 -> 12381.99 | H41: =CBNYQ-H42 -> 12537 | I41: =+G41-H41 -> -155.01 | J41: =CNYY-J42 -> 50729.72 | K41: =CBNYY-K42 -> 50148 | L41: =+J41-K41 -> 581.72 | Q41: 4127.33 | R41: =SUM(N41:Q41) -> 4127.33 | S41: =+D41 -> 4127.33 | T41: =+R41-S41 -> 0 | X41: 1190.95 | Y41: 45411.44 | Z41: =SUM(V41:Y41) -> 46602.39 | AA41: =+J41 -> 50729.72 | AB41: =+Z41-AA41 -> -4127.33 | AD41: Membership/Dues/Licenses | AE41: 0 | AF41: 1396.31 | AG41: 953.12 | AH41: 0 | AI41: =IF(AE41<>"",SUM(AE41:AH41),"") -> 2349.43
A42: EXE71470 | B42: SG&A: Occupancy Costs | C42: Lease Costs - Beamsville | D42: =LCDESOM -> 7500 | E42: =LCDESOBM -> 7644 | F42: =+D42-E42 -> -144 | G42: =LCDESOQ -> 25993.2 | H42: =LCDESOBQ -> 21945 | I42: =+G42-H42 -> 4048.2 | J42: =LCDESOY -> 77773.8 | K42: =LCDESOBY -> 74577 | L42: =+J42-K42 -> 3196.8 | O42: 7500 | R42: =SUM(N42:Q42) -> 7500 | S42: =+D42 -> 7500 | T42: =+R42-S42 -> 0 | W42: 70273.8 | Z42: =SUM(V42:Y42) -> 70273.8 | AA42: =+J42 -> 77773.8 | AB42: =+Z42-AA42 -> -7500 | AD42: Total General & Admin Expense | AE42: 307903.03 | AF42: 437098.22 | AG42: 109033.08 | AH42: 71652.98 | AI42: =IF(AE42<>"",SUM(AE42:AH42),"") -> 925687.31
A43: 417 | B43: SG&A: Office & General | C43: Office and General | D43: =CNYM -> 22917.62 | E43: =CBNYM -> 18262.07 | F43: =+D43-E43 -> 4655.55 | G43: =CNYQ -> 51967.28 | H43: =CBNYQ -> 42765.87 | I43: =+G43-H43 -> 9201.41 | J43: =CNYY -> 197967.56 | K43: =CBNYY -> 186262.66 | L43: =+J43-K43 -> 11704.9 | N43: 5360.11 | O43: 157 | P43: 5450.1 | Q43: 868.98 | R43: =SUM(N43:Q43) -> 11836.19 | S43: =+D43 -> 22917.62 | T43: =+R43-S43 -> -11081.43 | V43: 71682.11 | W43: 3006.5 | X43: 91438.48 | Y43: 8072.85 | Z43: =SUM(V43:Y43) -> 174199.94 | AA43: =+J43 -> 197967.56 | AB43: =+Z43-AA43 -> -23767.62 | AI43: =IF(AE43<>"",SUM(AE43:AH43),"")
A44: 418 | B44: SG&A: Professional Fees | C44: Professional Fees | D44: =CNYM -> 21399.08 | E44: =CBNYM -> 14293.61 | F44: =+D44-E44 -> 7105.47 | G44: =CNYQ -> 57354.61 | H44: =CBNYQ -> 42159.04 | I44: =+G44-H44 -> 15195.57 | J44: =CNYY -> 286240.54 | K44: =CBNYY -> 279932.56 | L44: =+J44-K44 -> 6307.98 | P44: 30630.85 | Q44: -311.31 | R44: =SUM(N44:Q44) -> 30319.54 | S44: =+D44 -> 21399.08 | T44: =+R44-S44 -> 8920.46 | X44: 274886.59 | Y44: -416.38 | Z44: =SUM(V44:Y44) -> 274470.21 | AA44: =+J44 -> 286240.54 | AB44: =+Z44-AA44 -> -11770.33 | AD44: Interest Expense | AI44: =IF(AE44<>"",SUM(AE44:AH44),"")
A45: 421 | B45: SG&A: Repairs/Maintenance | C45: R&M | D45: =CNYM -> 5976.81 | E45: =CBNYM -> 5186.81 | F45: =+D45-E45 -> 790 | G45: =CNYQ -> 23133.01 | H45: =CBNYQ -> 17691.76 | I45: =+G45-H45 -> 5441.25 | J45: =CNYY -> 97314.39 | K45: =CBNYY -> 70314.32 | L45: =+J45-K45 -> 27000.07 | N45: 2700.63 | O45: 50 | Q45: 21.22 | R45: =SUM(N45:Q45) -> 2771.85 | S45: =+D45 -> 5976.81 | T45: =+R45-S45 -> -3204.96 | V45: 75957.41 | W45: 11395.88 | Y45: 3984.29 | Z45: =SUM(V45:Y45) -> 91337.58 | AA45: =+J45 -> 97314.39 | AB45: =+Z45-AA45 -> -5976.81 | AD45: Financing Fees | AE45: 0.5 | AF45: 1806.87 | AG45: 0 | AI45: =IF(AE45<>"",SUM(AE45:AH45),"") -> 1807.37
A46: 426 | B46: SG&A: Telephone | C46: Telephone | D46: =CNYM -> 2727.96 | E46: =CBNYM -> 3135.98 | F46: =+D46-E46 -> -408.02 | G46: =CNYQ -> 8713.59 | H46: =CBNYQ -> 9255.54 | I46: =+G46-H46 -> -541.95 | J46: =CNYY -> 39052.1 | K46: =CBNYY -> 37115.21 | L46: =+J46-K46 -> 1936.89 | N46: 2194.48 | O46: 198.6 | P46: 821 | Q46: 194.41 | R46: =SUM(N46:Q46) -> 3408.49 | S46: =+D46 -> 2727.96 | T46: =+R46-S46 -> 680.53 | V46: 22332.38 | W46: 2373.96 | X46: 9505.62 | Y46: 2112.18 | Z46: =SUM(V46:Y46) -> 36324.14 | AA46: =+J46 -> 39052.1 | AB46: =+Z46-AA46 -> -2727.96 | AD46: Depreciation - Capital Assets | AE46: 867039.34 | AF46: 5469.14 | AG46: 0 | AH46: 5317.05 | AI46: =IF(AE46<>"",SUM(AE46:AH46),"") -> 877825.53
A47: 428 | B47: SG&A: Utilities | C47: Utilities | D47: =CNYM -> 2889.56 | E47: =CBNYM -> 1465.39 | F47: =+D47-E47 -> 1424.17 | G47: =CNYQ -> 8458.18 | H47: =CBNYQ -> 7576.98 | I47: =+G47-H47 -> 881.2 | J47: =CNYY -> 24583.42 | K47: =CBNYY -> 22032.29 | L47: =+J47-K47 -> 2551.13 | N47: 1082.36 | O47: 1013.16 | Q47: 523.27 | R47: =SUM(N47:Q47) -> 2618.79 | S47: =+D47 -> 2889.56 | T47: =+R47-S47 -> -270.77 | V47: 5877.66 | W47: 9571.59 | Y47: 6244.61 | Z47: =SUM(V47:Y47) -> 21693.86 | AA47: =+J47 -> 24583.42 | AB47: =+Z47-AA47 -> -2889.56 | AD47: Amortization - Intangibles | AE47: 1361.8 | AF47: 0 | AG47: 0 | AI47: =IF(AE47<>"",SUM(AE47:AH47),"") -> 1361.8
A48: 445 | B48: Membership/Dues/Licenses | C48: Memberships/dues/licenses | D48: =CNYM -> 137.08 | E48: =CBNYM -> 263.33 | F48: =+D48-E48 -> -126.25 | G48: =CNYQ -> 400.62 | H48: =CBNYQ -> 789.99 | I48: =+G48-H48 -> -389.37 | J48: =CNYY -> 2349.43 | K48: =CBNYY -> 3159.96 | L48: =+J48-K48 -> -810.53 | O48: 63.54 | P48: 10 | R48: =SUM(N48:Q48) -> 73.54 | S48: =+D48 -> 137.08 | T48: =+R48-S48 -> -63.54 | W48: 826.04 | X48: 1386.31 | Z48: =SUM(V48:Y48) -> 2212.35 | AA48: =+J48 -> 2349.43 | AB48: =+Z48-AA48 -> -137.08 | AD48: Interest - LTD | AE48: 77311.95 | AF48: 1086858.6 | AG48: 8470.16 | AH48: 4700 | AI48: =IF(AE48<>"",SUM(AE48:AH48),"") -> 1177340.8
A49: 805 | B49: Reorganization costs | C49: Re-organization costs | D49: =CNYM -> 0 | E49: =CBNYM -> 0 | F49: =+D49-E49 -> 0 | G49: =CNYQ -> 0 | H49: =CBNYQ -> 0 | I49: =+G49-H49 -> 0 | J49: =CNYY -> 0 | K49: =CBNYY -> 0 | L49: =+J49-K49 -> 0 | R49: =SUM(N49:Q49) -> 0 | S49: =+D49 -> 0 | T49: =+R49-S49 -> 0 | Z49: =SUM(V49:Y49) -> 0 | AA49: =+J49 -> 0 | AB49: =+Z49-AA49 -> 0 | AD49: Total Interest Expense | AE49: 945713.59 | AF49: 1094134.7 | AG49: 8470.16 | AH49: 10017.05 | AI49: =IF(AE49<>"",SUM(AE49:AH49),"") -> 2058335.5
A50: 899 | B50: Other expenses | C50: Other expenses | D50: =CNYM -> 0 | E50: =CBNYM -> 0 | F50: =+D50-E50 -> 0 | G50: =CNYQ -> 0 | H50: =CBNYQ -> 0 | I50: =+G50-H50 -> 0 | J50: =CNYY -> 0 | K50: =CBNYY -> 0 | L50: =+J50-K50 -> 0 | R50: =SUM(N50:Q50) -> 0 | S50: =+D50 -> 0 | T50: =+R50-S50 -> 0 | Z50: =SUM(V50:Y50) -> 0 | AA50: =+J50 -> 0 | AB50: =+Z50-AA50 -> 0 | AI50: =IF(AE50<>"",SUM(AE50:AH50),"")
A51: 901 | B51: Other Expenses | C51: Other expenses | D51: =CNYM -> 0 | E51: =CBNYM -> 0 | G51: =CNYQ -> 0 | H51: =CBNYQ -> 0 | J51: =CNYY -> 0 | K51: =CBNYY -> 0 | R51: =SUM(N51:Q51) -> 0 | S51: =+D51 -> 0 | T51: =+R51-S51 -> 0 | Z51: =SUM(V51:Y51) -> 0 | AA51: =+J51 -> 0 | AB51: =+Z51-AA51 -> 0 | AD51: Gain/Loss on Asset Disposal | AI51: =IF(AE51<>"",SUM(AE51:AH51),"")
C52: Total G&A | D52: =SUM(D38:D51) -> 132213.47 | E52: =SUM(E38:E51) -> 56699.19 | F52: =+D52-E52 -> 75514.28 | G52: =SUM(G38:G51) -> 261170.49 | H52: =SUM(H38:H51) -> 161528.18 | I52: =+G52-H52 -> 99642.31 | J52: =SUM(J38:J51) -> 878539.16 | K52: =SUM(K38:K51) -> 750770 | L52: =+J52-K52 -> 127769.16 | AD52: Gain/Loss on Sale of Assets | AE52: 0 | AF52: 0 | AG52: 0 | AH52: 0 | AI52: =IF(AE52<>"",SUM(AE52:AH52),"") -> 0
AD53: Total Gain/Loss on Asset Disposal | AE53: 0 | AF53: 0 | AG53: 0 | AH53: 0 | AI53: =IF(AE53<>"",SUM(AE53:AH53),"") -> 0
C54: TOTAL EXPENSES | D54: =D28+D35+D52 -> 352767.22 | E54: =E28+E35+E52 -> 384033.67 | F54: =+D54-E54 -> -31266.45 | G54: =G28+G35+G52 -> 1170745.1 | H54: =H28+H35+H52 -> 1048702.5 | I54: =+G54-H54 -> 122042.67 | J54: =J28+J35+J52 -> 5159964.4 | K54: =K28+K35+K52 -> 5445006.6 | L54: =+J54-K54 -> -285042.13 | AD54: INCOME (LOSS) BEFORE TAXES | AE54: 1408373.7 | AF54: -2154107.3 | AG54: -101009.96 | AH54: 56154.02 | AI54: =IF(AE54<>"",SUM(AE54:AH54),"") -> -790589.62
AI55: =IF(AE55<>"",SUM(AE55:AH55),"")
C56: EBITDA | D56: =D20-D54 -> -222693 | E56: =E20-E54 -> 68116.35 | F56: =+D56-E56 -> -290809.35 | G56: =G20-G54 -> -270669.15 | H56: =H20-H54 -> 152894.79 | I56: =+G56-H56 -> -423563.94 | J56: =J20-J54 -> 954734.58 | K56: =K20-K54 -> 2050115.1 | L56: =+J56-K56 -> -1095380.5 | AD56: Income Tax Expense | AI56: =IF(AE56<>"",SUM(AE56:AH56),"")
C57: EBITDA % | D57: =D56/D11 -> -0.21545588 | E57: =E56/E11 -> 0.054279099 | G57: =G56/G11 -> -0.096536643 | H57: =H56/H11 -> 0.053558263 | J57: =J56/J11 -> 0.065887547 | K57: =K56/K11 -> 0.12695708 | AD57: Other Expenses | AE57: 0 | AF57: 0 | AG57: 0 | AH57: 0 | AI57: =IF(AE57<>"",SUM(AE57:AH57),"") -> 0
AD58: Total Income Tax Expense | AE58: 0 | AF58: 0 | AG58: 0 | AH58: 0 | AI58: =IF(AE58<>"",SUM(AE58:AH58),"") -> 0
A59: 711 | B59: Interest - LTD | C59: Interest on bank indebtedness | D59: =CNYM -> 31774.05 | E59: =CBNYM -> 99397.58 | F59: =+D59-E59 -> -67623.53 | G59: =CNYQ -> 217649.25 | H59: =CBNYQ -> 298097.16 | I59: =+G59-H59 -> -80447.91 | J59: =CNYY -> 1113434.9 | K59: =CBNYY -> 1170611.7 | L59: =+J59-K59 -> -57176.79 | N59: 4241.94 | O59: 367.02 | P59: 80461.55 | Q59: 583.19 | R59: =SUM(N59:Q59) -> 85653.7 | S59: =+D59 -> 31774.05 | T59: =+R59-S59 -> 53879.65 | V59: 71920.78 | W59: 8005.15 | X59: 997728.12 | Y59: 4006.83 | Z59: =SUM(V59:Y59) -> 1081660.9 | AA59: =+J59 -> 1113434.9 | AB59: =+Z59-AA59 -> -31774.05 | AI59: =IF(AE59<>"",SUM(AE59:AH59),"")
A60: 446 | B60: Financing Fees | C60: Financing Costs | D60: =CNYM -> 0 | E60: =CBNYM -> 0 | F60: =+D60-E60 -> 0 | G60: =CNYQ -> 0 | H60: =CBNYQ -> 0 | I60: =+G60-H60 -> 0 | J60: =CNYY -> 1807.37 | K60: =CBNYY -> 180000 | L60: =+J60-K60 -> -178192.63 | R60: =SUM(N60:Q60) -> 0 | S60: =+D60 -> 0 | T60: =+R60-S60 -> 0 | X60: 1806.87 | Z60: =SUM(V60:Y60) -> 1806.87 | AA60: =+J60 -> 1807.37 | AB60: =+Z60-AA60 -> -0.5 | AD60: TOTAL EXPENSES | AE60: 12417938 | AF60: 2154107.3 | AG60: 314188.02 | AH60: 396791.49 | AI60: =IF(AE60<>"",SUM(AE60:AH60),"") -> 15283025
A61: 701 | B61: Depreciation - Capital Assets | C61: Depreciation of PP&E | D61: =CNYM -> 78264.5 | E61: =CBNYM -> 75433.66 | F61: =+D61-E61 -> 2830.84 | G61: =CNYQ -> 225936.19 | H61: =CBNYQ -> 226600.71 | I61: =+G61-H61 -> -664.52 | J61: =CNYY -> 882671.96 | K61: =CBNYY -> 899008.73 | L61: =+J61-K61 -> -16336.77 | N61: 72401.98 | P61: 911.52 | Q61: 443.09 | R61: =SUM(N61:Q61) -> 73756.59 | S61: =+D61 -> 78264.5 | T61: =+R61-S61 -> -4507.91 | V61: 794520.12 | X61: 5013.38 | Y61: 4873.96 | Z61: =SUM(V61:Y61) -> 804407.46 | AA61: =+J61 -> 882671.96 | AB61: =+Z61-AA61 -> -78264.5 | AD61: NET INCOME (LOSS) | AE61: 1408373.7 | AF61: -2154107.3 | AG61: -101009.96 | AH61: 56154.02 | AI61: =IF(AE61<>"",SUM(AE61:AH61),"") -> -790589.62
A62: 702 | B62: Amortization - Intangibles | C62: Amortization of Intangible Assets | D62: =CNYM -> 113.51 | E62: =CBNYM -> 67.48 | F62: =+D62-E62 -> 46.03 | G62: =CNYQ -> 340.47 | H62: =CBNYQ -> 202.44 | I62: =+G62-H62 -> 138.03 | J62: =CNYY -> 1361.8 | K62: =CBNYY -> 809.8 | L62: =+J62-K62 -> 552 | N62: 113.48 | R62: =SUM(N62:Q62) -> 113.48 | S62: =+D62 -> 113.51 | T62: =+R62-S62 -> -0.03 | V62: 1248.29 | Z62: =SUM(V62:Y62) -> 1248.29 | AA62: =+J62 -> 1361.8 | AB62: =+Z62-AA62 -> -113.51
C64: Extraordinary
C65: Loss from Operations | D65: =CNYM -> 0 | E65: =CBNYM -> 0 | G65: =CNYQ -> 0 | H65: =CBNYQ -> 0 | J65: =CNYY -> 0 | K65: =CBNYY -> 0
A66: 740 | B66: Gain/Loss on Sale of Assets | C66: Loss on disposal - assets held for sale | D66: =CNYM -> 0 | E66: =CBNYM -> 0 | G66: =CNYQ -> 0 | H66: =CBNYQ -> 0 | J66: =CNYY -> 0 | K66: =CBNYY -> 0
C67: Restructuring charges | E67: =CBNYM -> 0 | G67: =CNYQ -> 0 | H67: =CBNYQ -> 0 | J67: =CNYY -> 0 | K67: =CBNYY -> 0
C69: Net Income/Loss | D69: =D56-D59-D60-D61-D62-D65-D66-D67 -> -332845.06 | E69: =E56-E59-E60-E61-E62-E65-E66-E67 -> -106782.37 | F69: =+D69-E69 -> -226062.69 | G69: =G56-G59-G60-G61-G62-G65-G66-G67 -> -714595.06 | H69: =H56-H59-H60-H61-H62-H65-H66-H67 -> -372005.52 | I69: =+G69-H69 -> -342589.54 | J69: =J56-J59-J60-J61-J62-J65-J66-J67 -> -1044541.5 | K69: =K56-K59-K60-K61-K62-K65-K66-K67 -> -200315.2 | L69: =+J69-K69 -> -844226.28 | N69: =-(-N11+N16+N17+N18+N25+N26+N27+N31+N32+N33+N34+N38+N39+N40+N41+N42+N43+N44+N45+N46+N47+N48+N49+N50+N51+N59+N61+N60+N62) -> -88086.17 | O69: =-(-O11+O16+O17+O18+O25+O26+O27+O31+O32+O33+O34+O38+O39+O40+O41+O42+O43+O44+O45+O46+O47+O48+O49+O50+O51+O59+O61+O60+O62) -> -8571.65 | P69: =-(-P11+P16+P17+P18+P25+P26+P27+P31+P32+P33+P34+P38+P39+P40+P41+P42+P43+P44+P45+P46+P47+P48+P49+P50+P51+P59+P61+P60+P62) -> -159661.33 | Q69: =-(-Q11+Q16+Q17+Q18+Q25+Q26+Q27+Q31+Q32+Q33+Q34+Q38+Q39+Q40+Q41+Q42+Q43+Q44+Q45+Q46+Q47+Q48+Q49+Q50+Q51+Q59+Q61+Q60+Q62) -> 3076.89 | R69: =-(-R11+R16+R17+R18+R25+R26+R27+R31+R32+R33+R34+R38+R39+R40+R41+R42+R43+R44+R45+R46+R47+R48+R49+R50+R51+R59+R61+R60+R62) -> -253242.26 | S69: =+D69 -> -332845.06 | T69: =+R69-S69 -> 79602.8 | V69: =-(-V11+V16+V17+V18+V25+V26+V27+V31+V32+V33+V34+V38+V39+V40+V41+V42+V43+V44+V45+V46+V47+V48+V49+V50+V51+V59+V61+V60+V62) -> 3236698.6 | W69: =-(-W11+W16+W17+W18+W25+W26+W27+W31+W32+W33+W34+W38+W39+W40+W41+W42+W43+W44+W45+W46+W47+W48+W49+W50+W51+W59+W61+W60+W62) -> -81387.96 | X69: =-(-X11+X16+X17+X18+X25+X26+X27+X31+X32+X33+X34+X38+X39+X40+X41+X42+X43+X44+X45+X46+X47+X48+X49+X50+X51+X59+X61+X60+X62) -> -1978416 | Y69: =-(-Y11+Y16+Y17+Y18+Y25+Y26+Y27+Y31+Y32+Y33+Y34+Y38+Y39+Y40+Y41+Y42+Y43+Y44+Y45+Y46+Y47+Y48+Y49+Y50+Y51+Y59+Y61+Y60+Y62) -> 52881.01 | Z69: =-(-Z11+Z16+Z17+Z18+Z25+Z26+Z27+Z31+Z32+Z33+Z34+Z38+Z39+Z40+Z41+Z42+Z43+Z44+Z45+Z46+Z47+Z48+Z49+Z50+Z51+Z59+Z61+Z60+Z62) -> 1229775.7 | AA69: =+J69 -> -1044541.5 | AB69: =+Z69-AA69 -> 2274317.1
C72: Check:
C73: NC | D73: 108298.02 | E73: 87775.25 | J73: 1391630.2 | K73: 2206164.8
C74: DS | D74: 3107.68 | E74: -12698.98 | J74: -75589.66 | K74: -56128.31
C75: HO | D75: -204600.86 | E75: -179897.51 | J75: -2173388.1 | K75: -2401856.2
C76: DESTO | D76: 1322.93 | E76: -1961.13 | J76: 54203.94 | K76: 51504.61
C77: Total | D77: =SUM(D73:D76) -> -91872.23 | E77: =SUM(E73:E76) -> -106782.37 | J77: =SUM(J73:J76) -> -803143.65 | K77: =SUM(K73:K76) -> -200315.2
D78: =+D69-D77 -> -240972.83 | E78: =+E69-E77 -> 0 | J78: =+J69-J77 -> -241397.83 | K78: =+K69-K77 -> 2.3865141e-09
A97: CBNYM | B97: SUMIF(CISS[SubGroup],'TY IS'!$A97,(INDIRECT("CISS[BTY"&'TY IS'!$B$4&"]")))
A98: CBNYQ | B98: SUMPRODUCT((CISS[SubGroup]='TY IS'!$A98)*(INDIRECT("CISS[[BTY"&RIGHT("0"&'TY IS'!$B$3,2)&"]:[BTY"&RIGHT("0"&'TY IS'!$B$4,2)&"]]")))
A99: CBNYY | B99: SUMPRODUCT((CISS[SubGroup]='TY IS'!$A99)*(INDIRECT("CISS[[BTY01]:[BTY"&RIGHT("0"&'TY IS'!$B$4,2)&"]]")))
A100: CNYM | B100: SUMIF(CISS[SubGroup],'TY IS'!$A100,(INDIRECT("CISS[TY"&'TY IS'!$B$4&"]")))
A101: CNYQ | B101: SUMPRODUCT((CISS[SubGroup]='TY IS'!$A101)*(INDIRECT("CISS[[TY"&RIGHT("0"&'TY IS'!$B$3,2)&"]:[TY"&RIGHT("0"&'TY IS'!$B$4,2)&"]]")))
A102: CNYY | B102: SUMPRODUCT((CISS[SubGroup]='TY IS'!$A102)*(INDIRECT("CISS[[TY01]:[TY"&RIGHT("0"&'TY IS'!$B$4,2)&"]]")))
A103: DBM | B103: SUMIF(CSAS[ACCT],'TY IS'!$A103,(INDIRECT("CSAS[BTY"&'TY IS'!$B$4&"]")))
A104: DBQ | B104: SUMPRODUCT((CSAS[ACCT]='TY IS'!$A104)*(INDIRECT("CSAS[[BTY"&RIGHT("0"&'TY IS'!$B$3,2)&"]:[BTY"&RIGHT("0"&'TY IS'!$B$4,2)&"]]")))
A105: DBY | B105: SUMPRODUCT((CSAS[ACCT]='TY IS'!$A105)*(INDIRECT("CSAS[[BTY01]:[BTY"&RIGHT("0"&'TY IS'!$B$4,2)&"]]")))
A106: DM | B106: SUMIF(CSAS[ACCT],'TY IS'!$A106,(INDIRECT("CSAS[TY"&'TY IS'!$B$4&"]")))
A107: DQ | B107: SUMPRODUCT((CSAS[ACCT]='TY IS'!$A107)*(INDIRECT("CSAS[[TY"&RIGHT("0"&'TY IS'!$B$3,2)&"]:[TY"&RIGHT("0"&'TY IS'!$B$4,2)&"]]")))
A108: DY | B108: SUMPRODUCT((CSAS[ACCT]='TY IS'!$A108)*(INDIRECT("CSAS[[TY01]:[TY"&RIGHT("0"&'TY IS'!$B$4,2)&"]]")))
... A115: Print_Area | B115: 'TY IS'!$C$1:$L$72
A116: Formula

Sheet NY IS
C1: CONSOLIDATED INCOME STATEMENT
B3: =IFERROR(VLOOKUP($D$4,REFERENCE!$A$2:$C$13,3,FALSE),0) -> 01 | C3: YEAR: | D3: NEXT YEAR
B4: =IFERROR(VLOOKUP($D$4,REFERENCE!$A$2:$B$13,2,FALSE),0) -> 01 | C4: MONTH: | D4: APRIL
D7: MTD | E7: BMTD | F7: VAR | G7: QTD | H7: BQTD | I7: VAR | J7: YTD | K7: BYTD | L7: VAR
A9: 104 | B9: Revenue | D9: =CNYM -> 1586011.6 | E9: =CBNYM -> 1627169.2 | G9: {=SUMPRODUCT((CISS[SubGroup]=$A9)*(INDIRECT("CISS[[NY"&RIGHT("0"&$B$3,2)&"]:[NY"&RIGHT("0"&$B$4,2)&"]]")))} -> 1586011.6 | H9: =CBNYQ -> 1627169.2 | J9: {=SUMPRODUCT((CISS[SubGroup]=$A9)*(INDIRECT("CISS[[NY01]:[NY"&RIGHT("0"&$B$4,2)&"]]")))} -> 1586011.6 | K9: =CBNYY -> 1627169.2
A10: 106 | B10: Revenues: De Sousa (Toronto) | D10: =CNYM -> 32068.25 | E10: =CBNYM -> 36160.18 | G10: =CNYQ -> 32068.25 | H10: =CBNYQ -> 36160.18 | J10: =CNYY -> 32068.25 | K10: =CBNYY -> 36160.18
C11: REVENUE | D11: =SUM(D9:D10) -> 1618079.8 | E11: =SUM(E9:E10) -> 1663329.3 | G11: =SUM(G9:G10) -> 1618079.8 | H11: =SUM(H9:H10) -> 1663329.3 | J11: =SUM(J9:J10) -> 1618079.8 | K11: =SUM(K9:K10) -> 1663329.3
C13: COGS
A14: 201 | B14: COGS: DEWS (HO) | D14: =CNYM -> 12255.35 | E14: =CBNYM -> 14737.38 | G14: =CNYQ -> 12255.35 | H14: =CBNYQ -> 14737.38 | J14: =CNYY -> 12255.35 | K14: =CBNYY -> 14737.38
A15: 204 | B15: COGS: Product | D15: =CNYM -> 807258.39 | E15: =CBNYM -> 915281.75 | G15: =CNYQ -> 807258.39 | H15: =CBNYQ -> 915281.75 | J15: =CNYY -> 807258.39 | K15: =CBNYY -> 915281.75
C16: Cost of Product | D16: =SUM(D14:D15) -> 819513.74 | E16: =SUM(E14:E15) -> 930019.13 | G16: =SUM(G14:G15) -> 819513.74 | H16: =SUM(H14:H15) -> 930019.13 | J16: =SUM(J14:J15) -> 819513.74 | K16: =SUM(K14:K15) -> 930019.13
A17: 700 | B17: COGS - Other | C17: Cost of Product - Other | D17: =CNYM -> 17679 | E17: =CBNYM -> 13014 | G17: =CNYQ -> 17679 | H17: =CBNYQ -> 13014 | J17: =CNYY -> 17679 | K17: =CBNYY -> 13014
A18: 444 | B18: Freight/Warehousing | C18: Freight and Warehousing | D18: =CNYM -> -5115.14 | E18: =CBNYM -> 18317.26 | G18: =CNYQ -> -5115.14 | H18: =CBNYQ -> 18317.26 | J18: =CNYY -> -5115.14 | K18: =CBNYY -> 18317.26
C19: Total COGS | D19: =SUM(D16:D18) -> 832077.6 | E19: =SUM(E16:E18) -> 961350.39 | G19: =SUM(G16:G18) -> 832077.6 | H19: =SUM(H16:H18) -> 961350.39 | J19: =SUM(J16:J18) -> 832077.6 | K19: =SUM(K16:K18) -> 961350.39
C20: Gross Margin | D20: =D11-D19 -> 786002.2 | E20: =E11-E19 -> 701978.96 | G20: =G11-G19 -> 786002.2 | H20: =H11-H19 -> 701978.96 | J20: =J11-J19 -> 786002.2 | K20: =K11-K19 -> 701978.96
C21: Gross Margin % | D21: =IFERROR(D20/D11,0) -> 0.48576232 | E21: =IFERROR(E20/E11,0) -> 0.42203245 | G21: =IFERROR(G20/G11,0) -> 0.48576232 | H21: =IFERROR(H20/H11,0) -> 0.42203245 | J21: =IFERROR(J20/J11,0) -> 0.48576232 | K21: =IFERROR(K20/K11,0) -> 0.42203245
C23: EXPENSE
C24: Personnel costs
A25: 409 | B25: SG&A: Employee Benefits | C25: Employee Comp & benefits | D25: =CNYM -> 73381.72 | E25: =CBNYM -> 128811.39 | G25: =CNYQ -> 73381.72 | H25: =CBNYQ -> 128811.39 | J25: =CNYY -> 73381.72 | K25: =CBNYY -> 128811.39
A26: 404 | B26: SG&A: Automotive | C26: Automobile | D26: =CNYM -> 8147.77 | E26: =CBNYM -> 9502.85 | G26: =CNYQ -> 8147.77 | H26: =CBNYQ -> 9502.85 | J26: =CNYY -> 8147.77 | K26: =CBNYY -> 9502.85
C27: Share Based payments | D27: =CNYM -> 0 | E27: =CBNYM -> 0 | G27: =CNYQ -> 0 | H27: =CBNYQ -> 0 | J27: =CNYY -> 0 | K27: =CBNYY -> 0
C28: Total Personnel Costs | D28: =SUM(D25:D27) -> 81529.49 | E28: =SUM(E25:E27) -> 138314.24 | G28: =SUM(G25:G27) -> 81529.49 | H28: =SUM(H25:H27) -> 138314.24 | J28: =SUM(J25:J27) -> 81529.49 | K28: =SUM(K25:K27) -> 138314.24
C30: Sales & Marketing
A31: 407 | B31: SG&A: Commissions | C31: Commissions | D31: =CNYM -> 67644.69 | E31: =CBNYM -> 82282.56 | G31: =CNYQ -> 67644.69 | H31: =CBNYQ -> 82282.56 | J31: =CNYY -> 67644.69 | K31: =CBNYY -> 82282.56
A32: 401 | B32: SG&A: Advertising | C32: Advertising & Promotions | D32: =CNYM-D33 -> 96795.05 | E32: =CBNYM-E33 -> 133162.38 | G32: =CNYQ-G33 -> 96795.05 | H32: =CBNYQ-H33 -> 133162.38 | J32: =CNYY-J33 -> 96795.05 | K32: =CBNYY-K33 -> 133162.38
A33: 71550 | B33: SG&A: Advertising | C33: Donations | D33: =DM -> 0 | E33: =DBM -> 1665.32 | G33: =DQ -> 0 | H33: =DBQ -> 1665.32 | J33: =DY -> 0 | K33: =DBY -> 1665.32
A34: 440 | B34: Royalties | C34: Royalties | D34: =CNYM -> 12430.36 | E34: =CBNYM -> 17683.39 | G34: =CNYQ -> 12430.36 | H34: =CBNYQ -> 17683.39 | J34: =CNYY -> 12430.36 | K34: =CBNYY -> 17683.39
C35: Total Sales & Marketing | D35: =SUM(D31:D34) -> 176870.1 | E35: =SUM(E31:E34) -> 234793.65 | G35: =SUM(G31:G34) -> 176870.1 | H35: =SUM(H31:H34) -> 234793.65 | J35: =SUM(J31:J34) -> 176870.1 | K35: =SUM(K31:K34) -> 234793.65
E36: =CBNYM -> 0
C37: G&A | E37: =CBNYM -> 0
A38: 405 | B38: SG&A: Bad Debts | C38: Bad Debts | D38: =CNYM -> -1224.15 | E38: =CBNYM -> 799.15 | G38: =CNYQ -> -1224.15 | H38: =CBNYQ -> 799.15 | J38: =CNYY -> -1224.15 | K38: =CBNYY -> 799.15
A39: 412 | B39: SG&A: Insurance | C39: Insurance | D39: =CNYM -> 1490.03 | E39: =CBNYM -> 3138.05 | G39: =CNYQ -> 1490.03 | H39: =CBNYQ -> 3138.05 | J39: =CNYY -> 1490.03 | K39: =CBNYY -> 3138.05
A40: 415 | B40: SG&A: Management Fees | C40: Management Fees | D40: =CNYM -> 0 | E40: =CBNYM -> 0 | G40: =CNYQ -> 0 | H40: =CBNYQ -> 0 | J40: =CNYY -> 0 | K40: =CBNYY -> 0
A41: 416 | B41: SG&A: Occupancy Costs | C41: Occupancy costs | D41: =CNYM-D42 -> 3849.25 | E41: =CBNYM-E42 -> 4428.39 | G41: =CNYQ-G42 -> 3849.25 | H41: =CBNYQ-H42 -> 4428.39 | J41: =CNYY-J42 -> 3849.25 | K41: =CBNYY-K42 -> 4428.39
A42: EXE71470 | B42: SG&A: Occupancy Costs | C42: Lease Costs - Beamsville | D42: =LCDESOM -> -77773.8 | E42: =LCDESOBM -> 7500 | G42: =LCDESOQ -> -77773.8 | H42: =LCDESOBQ -> 7500 | J42: =LCDESOY -> -77773.8 | K42: =LCDESOBY -> 7500
A43: 417 | B43: SG&A: Office & General | C43: Office and General | D43: =CNYM -> 12070.6 | E43: =CBNYM -> 19506.97 | G43: =CNYQ -> 12070.6 | H43: =CBNYQ -> 19506.97 | J43: =CNYY -> 12070.6 | K43: =CBNYY -> 19506.97
A44: 418 | B44: SG&A: Professional Fees | C44: Professional Fees | D44: =CNYM -> 5048.76 | E44: =CBNYM -> 19306.67 | G44: =CNYQ -> 5048.76 | H44: =CBNYQ -> 19306.67 | J44: =CNYY -> 5048.76 | K44: =CBNYY -> 19306.67
A45: 421 | B45: SG&A: Repairs/Maintenance | C45: R&M | D45: =CNYM -> -7126.02 | E45: =CBNYM -> 11174.86 | G45: =CNYQ -> -7126.02 | H45: =CBNYQ -> 11174.86 | J45: =CNYY -> -7126.02 | K45: =CBNYY -> 11174.86
A46: 426 | B46: SG&A: Telephone | C46: Telephone | D46: =CNYM -> -217.89 | E46: =CBNYM -> 3031.36 | G46: =CNYQ -> -217.89 | H46: =CBNYQ -> 3031.36 | J46: =CNYY -> -217.89 | K46: =CBNYY -> 3031.36
A47: 428 | B47: SG&A: Utilities | C47: Utilities | D47: =CNYM -> -11145.43 | E47: =CBNYM -> 2208.29 | G47: =CNYQ -> -11145.43 | H47: =CBNYQ -> 2208.29 | J47: =CNYY -> -11145.43 | K47: =CBNYY -> 2208.29
A48: 445 | B48: Membership/Dues/Licenses | C48: Memberships/dues/licenses | D48: =CNYM -> -943.12 | E48: =CBNYM -> 11.15 | G48: =CNYQ -> -943.12 | H48: =CBNYQ -> 11.15 | J48: =CNYY -> -943.12 | K48: =CBNYY -> 11.15
A49: 805 | B49: Reorganization costs | C49: Re-organization costs | D49: =CNYM -> 0 | E49: =CBNYM -> 0 | G49: =CNYQ -> 0 | H49: =CBNYQ -> 0 | J49: =CNYY -> 0 | K49: =CBNYY -> 0
A50: 899 | B50: Other expenses | C50: Other expenses | D50: =CNYM -> 0 | E50: =CBNYM -> 0 | G50: =CNYQ -> 0 | H50: =CBNYQ -> 0 | J50: =CNYY -> 0 | K50: =CBNYY -> 0
A51: 901 | B51: Other Expenses | C51: Other expenses | D51: =CNYM -> 0 | E51: =CBNYM -> 0 | G51: =CNYQ -> 0 | H51: =CBNYQ -> 0 | J51: =CNYY -> 0 | K51: =CBNYY -> 0
C52: Total G&A | D52: =SUM(D38:D51) -> -75971.77 | E52: =SUM(E38:E51) -> 71104.89 | G52: =SUM(G38:G51) -> -75971.77 | H52: =SUM(H38:H51) -> 71104.89 | J52: =SUM(J38:J51) -> -75971.77 | K52: =SUM(K38:K51) -> 71104.89
C54: TOTAL EXPENSES | D54: =D28+D35+D52 -> 182427.82 | E54: =E28+E35+E52 -> 444212.78 | G54: =G28+G35+G52 -> 182427.82 | H54: =H28+H35+H52 -> 444212.78 | J54: =J28+J35+J52 -> 182427.82 | K54: =K28+K35+K52 -> 444212.78
C56: EBITDA | D56: =D20-D54 -> 603574.38 | E56: =E20-E54 -> 257766.18 | G56: =G20-G54 -> 603574.38 | H56: =H20-H54 -> 257766.18 | J56: =J20-J54 -> 603574.38 | K56: =K20-K54 -> 257766.18
C57: EBITDA % | D57: =IFERROR(D56/D11,0) -> 0.37301892 | E57: =IFERROR(E56/E11,0) -> 0.15497002 | G57: =IFERROR(G56/G11,0) -> 0.37301892 | H57: =IFERROR(H56/H11,0) -> 0.15497002 | J57: =IFERROR(J56/J11,0) -> 0.37301892 | K57: =IFERROR(K56/K11,0) -> 0.15497002
A59: 711 | B59: Interest - LTD | C59: Interest on bank indebtedness | D59: =CNYM -> 123453.96 | E59: =CBNYM -> 86529 | G59: =CNYQ -> 123453.96 | H59: =CBNYQ -> 86529 | J59: =CNYY -> 123453.96 | K59: =CBNYY -> 86529
A60: 446 | B60: Financing Fees | C60: Financing Costs | D60: =CNYM -> 0 | E60: =CBNYM -> 0 | G60: =CNYQ -> 0 | H60: =CBNYQ -> 0 | J60: =CNYY -> 0 | K60: =CBNYY -> 0
A61: 701 | B61: Depreciation - Capital Assets | C61: Depreciation of PP&E | D61: =CNYM -> -0.01 | E61: =CBNYM -> 67833.19 | G61: =CNYQ -> -0.01 | H61: =CBNYQ -> 67833.19 | J61: =CNYY -> -0.01 | K61: =CBNYY -> 67833.19
A62: 702 | B62: Amortization - Intangibles | C62: Amortization of Intangible Assets | D62: =CNYM -> 0 | E62: =CBNYM -> 90.78 | G62: =CNYQ -> 0 | H62: =CBNYQ -> 90.78 | J62: =CNYY -> 0 | K62: =CBNYY -> 90.78
C64: Extraordinary
C65: Loss from Operations | D65: =CNYM -> 0 | E65: =CBNYM -> 0 | G65: =CNYQ -> 0 | H65: =CBNYQ -> 0 | J65: =CNYY -> 0 | K65: =CBNYY -> 0
A66: 740 | B66: Gain/Loss on Sale of Assets | C66: Loss on disposal - assets held for sale | D66: =CNYM -> 0 | E66: =CBNYM -> 0 | G66: =CNYQ -> 0 | H66: =CBNYQ -> 0 | J66: =CNYY -> 0 | K66: =CBNYY -> 0
C67: Restructuring charges | E67: =CBNYM -> 0 | G67: =CNYQ -> 0 | H67: =CBNYQ -> 0 | J67: =CNYY -> 0 | K67: =CBNYY -> 0
C69: Net Income/Loss | D69: =D56-D59-D60-D61-D62-D65-D66-D67 -> 480120.43 | E69: =E56-E59-E60-E61-E62-E65-E66-E67 -> 103313.21 | G69: =G56-G59-G60-G61-G62-G65-G66-G67 -> 480120.43 | H69: =H56-H59-H60-H61-H62-H65-H66-H67 -> 103313.21 | J69: =J56-J59-J60-J61-J62-J65-J66-J67 -> 480120.43 | K69: =K56-K59-K60-K61-K62-K65-K66-K67 -> 103313.21
K71: 111382
K72: =+K69-K71 -> -8068.79
A80: CBNYM | B80: SUMIF(CISS[SubGroup],'NY IS'!$A80,(INDIRECT("CISS[BNY"&'NY IS'!$B$4&"]")))
A81: CBNYQ | B81: SUMPRODUCT((CISS[SubGroup]='NY IS'!$A81)*(INDIRECT("CISS[[BNY"&RIGHT("0"&'NY IS'!$B$3,2)&"]:[BNY"&RIGHT("0"&'NY IS'!$B$4,2)&"]]")))
A82: CBNYY | B82: SUMPRODUCT((CISS[SubGroup]='NY IS'!$A82)*(INDIRECT("CISS[[BNY01]:[BNY"&RIGHT("0"&'NY IS'!$B$4,2)&"]]")))
A83: CNYM | B83: SUMIF(CISS[SubGroup],'NY IS'!$A83,(INDIRECT("CISS[NY"&'NY IS'!$B$4&"]")))
A84: CNYQ | B84: SUMPRODUCT((CISS[SubGroup]='NY IS'!$A84)*(INDIRECT("CISS[[NY"&RIGHT("0"&'NY IS'!$B$3,2)&"]:[NY"&RIGHT("0"&'NY IS'!$B$4,2)&"]]")))
A85: CNYY | B85: SUMPRODUCT((CISS[SubGroup]='NY IS'!$A85)*(INDIRECT("CISS[[NY01]:[NY"&RIGHT("0"&'NY IS'!$B$4,2)&"]]")))
A86: DBM | B86: SUMIF(CSAS[ACCT],'NY IS'!$A86,(INDIRECT("CSAS[BNY"&'NY IS'!$B$4&"]")))
A87: DBQ | B87: SUMPRODUCT((CSAS[ACCT]='NY IS'!$A87)*(INDIRECT("CSAS[[BNY"&RIGHT("0"&'NY IS'!$B$3,2)&"]:[BNY"&RIGHT("0"&'NY IS'!$B$4,2)&"]]")))
A88: DBY | B88: SUMPRODUCT((CSAS[ACCT]='NY IS'!$A88)*(INDIRECT("CSAS[[BNY01]:[BNY"&RIGHT("0"&'NY IS'!$B$4,2)&"]]")))
A89: DM | B89: SUMIF(CSAS[ACCT],'NY IS'!$A89,(INDIRECT("CSAS[NY"&'NY IS'!$B$4&"]")))
A90: DQ | B90: SUMPRODUCT((CSAS[ACCT]='NY IS'!$A90)*(INDIRECT("CSAS[[NY"&RIGHT("0"&'NY IS'!$B$3,2)&"]:[NY"&RIGHT("0"&'NY IS'!$B$4,2)&"]]")))
A91: DY | B91: SUMPRODUCT((CSAS[ACCT]='NY IS'!$A91)*(INDIRECT("CSAS[[NY01]:[NY"&RIGHT("0"&'NY IS'!$B$4,2)&"]]")))
... A98: Print_Area | B98: 'NY IS'!$C$1:$L$72
A99: Formula

Sheet DataSource
A1: SubGroup | B1: SubGroup_Name | C1: LY01 | D1: LY02 | E1: LY03 | F1: LY04 | G1: LY05 | H1: LY06 | I1: LY07 | J1: LY08 | K1: LY09 | L1: LY10 | M1: LY11 | N1: LY12 | O1: TY01 | P1: TY02 | Q1: TY03 | R1: TY04 | S1: TY05 | T1: TY06 | U1: TY07 | V1: TY08 | W1: TY09 | X1: TY10 | Y1: TY11 | Z1: TY12 | AA1: NY01 | AB1: NY02 | AC1: NY03 | AD1: NY04 | AE1: NY05 | AF1: NY06 | AG1: NY07 | AH1: NY08 | AI1: NY09 | AJ1: NY10 | AK1: NY11 | AL1: NY12 | AM1: BLY01 | AN1: BLY02 | AO1: BLY03 | AP1: BLY04 | AQ1: BLY05 | AR1: BLY06 | AS1: BLY07 | AT1: BLY08 | AU1: BLY09 | AV1: BLY10 | AW1: BLY11 | AX1: BLY12 | AY1: BTY01 | AZ1: BTY02 | BA1: BTY03 | BB1: BTY04 | BC1: BTY05 | BD1: BTY06 | BE1: BTY07 | BF1: BTY08 | BG1: BTY09 | BH1: BTY10 | BI1: BTY11 | BJ1: BTY12 | BK1: BNY01 | BL1: BNY02 | BM1: BNY03 | BN1: BNY04 | BO1: BNY05 | BP1: BNY06 | BQ1: BNY07 | BR1: BNY08 | BS1: BNY09 | BT1: BNY10 | BU1: BNY11 | BV1: BNY12
A2: 104 | B2: Revenue | C2: 1125101.1 | D2: 1174153.8 | E2: 1306565 | F2: 1219494.4 | G2: 1421797.9 | H2: 1406953.2 | I2: 1415502 | J2: 805900.75 | K2: 920773.58 | L2: 659552.55 | M2: 1048904.9 | N2: 1140859.4 | O2: 1101854.3 | P2: 1439577.6 | Q2: 1136161.2 | R2: 1226515.4 | S2: 1096604.1 | T2: 1472597.5 | U2: 1751603.4 | V2: 1261046.7 | W2: 848344.56 | X2: 1000297.6 | Y2: 708412.51 | Z2: 998987.72 | AA2: 1586011.6 | AB2: 899683.19 | AC2: 771.75 | AD2: 771.75 | AE2: 771.75 | AF2: 771.75 | AG2: 771.75 | AH2: 771.75 | AI2: 771.75 | AJ2: 0 | AK2: 0 | AL2: 0 | AM2: 0 | AN2: 0 | AO2: 0 | AP2: 0 | AQ2: 0 | AR2: 0 | AS2: 0 | AT2: 0 | AU2: 0 | AV2: 0 | AW2: 0 | AX2: 0 | AY2: 1171090.9 | AZ2: 2085140.5 | BA2: 1066903.7 | BB2: 1196026.8 | BC2: 1048255.6 | BD2: 2237545.1 | BE2: 1618727.1 | BF2: 1380928.2 | BG2: 1138805.9 | BH2: 738559.19 | BI2: 810168.81 | BJ2: 1222999.1 | BK2: 1627169.2 | BL2: 2215616.6 | BM2: 1048863.9 | BN2: 813611.57 | BO2: 949913.8 | BP2: 3768364.5 | BQ2: 2113905.3 | BR2: 929872.62 | BS2: 859493.39 | BT2: 676738.61 | BU2: 836697.84 | BV2: 584879.92
A3: 106 | B3: Revenues: De Sousa (Toronto) | C3: 35559.51 | D3: 33343.03 | E3: 35628.62 | F3: 36408.44 | G3: 43945.08 | H3: 38083.22 | I3: 41771.35 | J3: 37202.06 | K3: 58707.35 | L3: 25193.35 | M3: 24798.03 | N3: 30167.91 | O3: 50661.55 | P3: 39317.66 | Q3: 44711.79 | R3: 37419.52 | S3: 32659.1 | T3: 31905.85 | U3: 33598.38 | V3: 33561.33 | W3: 48427.68 | X3: 29923.66 | Y3: 31573.44 | Z3: 34602.1 | AA3: 32068.25 | AB3: 25553.84 | AC3: 0 | AD3: 0 | AE3: 0 | AF3: 0 | AG3: 0 | AH3: 0 | AI3: 0 | AJ3: 0 | AK3: 0 | AL3: 0 | AM3: 41242.52 | AN3: 38616.51 | AO3: 41688.95 | AP3: 40627.92 | AQ3: 45204.54 | AR3: 36500.45 | AS3: 42193.91 | AT3: 40940.44 | AU3: 57175.44 | AV3: 34237.04 | AW3: 33694.6 | AX3: 40730.64 | AY3: 37059.5 | AZ3: 33514.94 | BA3: 36820.49 | BB3: 35936.4 | BC3: 42010.06 | BD3: 35326.63 | BE3: 37387.17 | BF3: 34986.65 | BG3: 56892.73 | BH3: 25000.63 | BI3: 26081.21 | BJ3: 31928.64 | BK3: 36160.18 | BL3: 35823.69 | BM3: 37584.76 | BN3: 37593.27 | BO3: 35520.73 | BP3: 35253.43 | BQ3: 38394.42 | BR3: 39446.15 | BS3: 53436.77 | BT3: 32417.08 | BU3: 33002.19 | BV3: 38920.29
A4: 201 | B4: COGS: DEWS (HO) | C4: 14522.29 | D4: 13914.12 | E4: 13003.33 | F4: 14460.35 | G4: 16721.84 | H4: 14506.69 | I4: 17348.69 | J4: 14750.64 | K4: 24593.33 | L4: 10393.37 | M4: 10820.9 | N4: 13851.05 | O4: 23590.74 | P4: 17346.2 | Q4: 19370.66 | R4: 13908.37 | S4: 13099.53 | T4: 15836.28 | U4: 13314.6 | V4: 9710.3 | W4: 19299.92 | X4: 12408.63 | Y4: 12520.03 | Z4: 14000.95 | AA4: 12255.35 | AB4: 7604.52 | AC4: 0 | AD4: 0 | AE4: 0 | AF4: 0 | AG4: 0 | AH4: 0 | AI4: 0 | AJ4: 0 | AK4: 0 | AL4: 0 | AM4: 15766.39 | AN4: 14972.18 | AO4: 16068.68 | AP4: 15720.84 | AQ4: 16915.75 | AR4: 14140.39 | AS4: 16241.83 | AT4: 16230.75 | AU4: 22446.94 | AV4: 13434.54 | AW4: 12831.11 | AX4: 15294.81 | AY4: 14913.46 | AZ4: 14409.75 | BA4: 14520.64 | BB4: 14191.46 | BC4: 16619.52 | BD4: 13886.97 | BE4: 15966.45 | BF4: 13996.85 | BG4: 20994.94 | BH4: 11178.37 | BI4: 11142.66 | BJ4: 15039.43 | BK4: 14737.38 | BL4: 14785.21 | BM4: 15053.45 | BN4: 15350.54 | BO4: 14709.24 | BP4: 14356.76 | BQ4: 15637.68 | BR4: 15924.62 | BS4: 21548.51 | BT4: 13509.13 | BU4: 13800.11 | BV4: 15982.93
A5: 204 | B5: COGS: Product | C5: 577558.09 | D5: 607380.36 | E5: 708712.53 | F5: 610312.55 | G5: 773614.41 | H5: 737264.15 | I5: 737618.12 | J5: 388896.42 | K5: 471673.41 | L5: 311513.24 | M5: 567757.71 | N5: 564626.83 | O5: 578137.84 | P5: 798212.77 | Q5: 489962.61 | R5: 619379.55 | S5: 429425.2 | T5: 659937.16 | U5: 883718.46 | V5: 529902.48 | W5: 533341.1 | X5: 386253.76 | Y5: 301298.51 | Z5: 531731.16 | AA5: 807258.39 | AB5: 482.32 | AC5: 0 | AD5: 0 | AE5: 0 | AF5: 0 | AG5: 0 | AH5: 0 | AI5: 0 | AJ5: 0 | AK5: 0 | AL5: 0 | AM5: 0 | AN5: 0 | AO5: 0 | AP5: 0 | AQ5: 0 | AR5: 0 | AS5: 0 | AT5: 0 | AU5: 0 | AV5: 0 | AW5: 0 | AX5: 0 | AY5: 620595.81 | AZ5: 1062927.8 | BA5: 497277.23 | BB5: 594075.07 | BC5: 504164.98 | BD5: 1162527.3 | BE5: 817061.61 | BF5: 707377.02 | BG5: 552355.55 | BH5: 371618.49 | BI5: 409727.43 | BJ5: 524192.19 | BK5: 915281.75 | BL5: 1237470.4 | BM5: 566126.76 | BN5: 435769.03 | BO5: 493214.52 | BP5: 2172432.4 | BQ5: 1131567.1 | BR5: 461898.06 | BS5: 432378.99 | BT5: 344362 | BU5: 308072.22 | BV5: 286945.82
A6: 401 | B6: SG&A: Advertising | C6: 130467.34 | D6: 200729.77 | E6: 194797.53 | F6: 171346 | G6: 106190.35 | H6: 207189.97 | I6: 152111.57 | J6: 150502.15 | K6: 80390.37 | L6: 86557.12 | M6: 60886.62 | N6: 178973.54 | O6: 74829.72 | P6: 90967.24 | Q6: 216029.23 | R6: 56454.57 | S6: 209599.03 | T6: 145862.02 | U6: 296880.37 | V6: 103275.55 | W6: 251289.18 | X6: 105208.22 | Y6: 178293.91 | Z6: 29002.96 | AA6: 96795.05 | AB6: 6755.19 | AC6: 0 | AD6: 0 | AE6: 0 | AF6: 0 | AG6: 0 | AH6: 0 | AI6: 0 | AJ6: 0 | AK6: 0 | AL6: 0 | AM6: 1965.07 | AN6: 261.28 | AO6: 2754.43 | AP6: 1244.44 | AQ6: 3222.2 | AR6: -741.9 | AS6: 482 | AT6: 250.02 | AU6: 1146.06 | AV6: 422.09 | AW6: 1691.29 | AX6: 1629.54 | AY6: 82449.64 | AZ6: 209623.07 | BA6: 175210.81 | BB6: 153026.1 | BC6: 126655.88 | BD6: 144250.62 | BE6: 284971.3 | BF6: 193146.95 | BG6: 186067.38 | BH6: 88067.11 | BI6: 82660.73 | BJ6: 119551.63 | BK6: 134827.7 | BL6: 181953.39 | BM6: 206775.28 | BN6: 116403.01 | BO6: 123150.31 | BP6: 161067.42 | BQ6: 302511.49 | BR6: 124632.66 | BS6: 197995.81 | BT6: 94288.74 | BU6: 56126.09 | BV6: 107649.78
A7: 404 | B7: SG&A: Automotive | C7: 0 | D7: 16.73 | E7: 0 | F7: 0 | G7: 0 | H7: 0 | I7: 0 | J7: 0 | K7: 0 | L7: 0 | M7: 0 | N7: 0 | O7: 5835.15 | P7: 9148.55 | Q7: 8950.68 | R7: 6894.23 | S7: 7974.1 | T7: 7749.59 | U7: 7808.37 | V7: 8028.77 | W7: 8238.25 | X7: 8024.12 | Y7: 7447.46 | Z7: 7455.07 | AA7: 8147.77 | AB7: 1000 | AC7: 0 | AD7: 0 | AE7: 0 | AF7: 0 | AG7: 0 | AH7: 0 | AI7: 0 | AJ7: 0 | AK7: 0 | AL7: 0 | AM7: 0 | AN7: 0 | AO7: 0 | AP7: 0 | AQ7: 0 | AR7: 0 | AS7: 0 | AT7: 0 | AU7: 0 | AV7: 0 | AW7: 0 | AX7: 0 | AY7: 6814.82 | AZ7: 6823.91 | BA7: 6749.93 | BB7: 6788.07 | BC7: 6858.31 | BD7: 7006.8 | BE7: 7006.8 | BF7: 6988.07 | BG7: 6930.53 | BH7: 7009.57 | BI7: 7428.98 | BJ7: 7801.68 | BK7: 9502.85 | BL7: 9351.76 | BM7: 9675.78 | BN7: 9859.66 | BO7: 9733.89 | BP7: 9812.07 | BQ7: 9822.77 | BR7: 9667.13 | BS7: 9635.72 | BT7: 9550.72 | BU7: 9537.72 | BV7: 9725.72
A8: 405 | B8: SG&A: Bad Debts | C8: 0 | D8: 1177.8 | E8: 1000 | F8: -3350.56 | G8: 0 | H8: 3412.07 | I8: 0 | J8: 200 | K8: 228.27 | L8: 0 | M8: 0 | N8: -28633.64 | O8: -311.26 | P8: 0 | Q8: 0 | R8: -2468.26 | S8: -193.4 | T8: 8441.34 | U8: 38.19 | V8: 2163.72 | W8: 136.12 | X8: 0 | Y8: 0 | Z8: 60423.04 | AA8: -1224.15 | AB8: 0 | AC8: 0 | AD8: 0 | AE8: 0 | AF8: 0 | AG8: 0 | AH8: 0 | AI8: 0 | AJ8: 0 | AK8: 0 | AL8: 0 | AM8: 0 | AN8: 0 | AO8: 0 | AP8: 0 | AQ8: 0 | AR8: 0 | AS8: 0 | AT8: 0 | AU8: 0 | AV8: 0 | AW8: 0 | AX8: 0 | AY8: 200 | AZ8: 200 | BA8: 200 | BB8: 200 | BC8: 200 | BD8: 200 | BE8: 200 | BF8: 200 | BG8: 200 | BH8: 200 | BI8: 200 | BJ8: 200 | BK8: 799.15 | BL8: 878.52 | BM8: 990.13 | BN8: 886.04 | BO8: 972.8 | BP8: 1017.64 | BQ8: 953.2 | BR8: 835.88 | BS8: 1038.62 | BT8: 678.13 | BU8: 690.7 | BV8: 734.97
A9: 407 | B9: SG&A: Commissions | C9: 73652.66 | D9: 88600.28 | E9: 85835.14 | F9: 84565.4 | G9: 106415.51 | H9: 109977.46 | I9: 84330.97 | J9: 65436.15 | K9: 75669.1 | L9: 52297.63 | M9: 60762.36 | N9: 58716.3 | O9: 77893.18 | P9: 61207.73 | Q9: 61095.56 | R9: 97542.97 | S9: 75854.21 | T9: 94400.11 | U9: 76227.69 | V9: 86286.62 | W9: 86773.65 | X9: 77989.41 | Y9: 66557.83 | Z9: 68157.54 | AA9: 67644.69 | AB9: 149.24 | AC9: 0 | AD9: 0 | AE9: 0 | AF9: 0 | AG9: 0 | AH9: 0 | AI9: 0 | AJ9: 0 | AK9: 0 | AL9: 0 | AM9: 0 | AN9: 0 | AO9: 0 | AP9: 0 | AQ9: 0 | AR9: 0 | AS9: 0 | AT9: 0 | AU9: 0 | AV9: 0 | AW9: 0 | AX9: 0 | AY9: 97229.44 | AZ9: 98757.09 | BA9: 93932.15 | BB9: 99093.88 | BC9: 97495.35 | BD9: 115827.82 | BE9: 134047.62 | BF9: 122784.28 | BG9: 103855.25 | BH9: 62341.45 | BI9: 70519.2 | BJ9: 70019.9 | BK9: 82282.56 | BL9: 98559.71 | BM9: 89741.51 | BN9: 78969.12 | BO9: 90954.95 | BP9: 96243.06 | BQ9: 90133.1 | BR9: 84556.77 | BS9: 82607.43 | BT9: 64499.8 | BU9: 55183.03 | BV9: 55149.26
A10: 409 | B10: SG&A: Employee Benefits | C10: 24981.52 | D10: 30194.39 | E10: 33641.49 | F10: 36782.56 | G10: 39955.58 | H10: 35512.45 | I10: 31497.42 | J10: 27849.49 | K10: 32134.75 | L10: 28606.21 | M10: 24151.09 | N10: 29778.31 | O10: 130483.19 | P10: 173587.02 | Q10: 41781.27 | R10: 141579.75 | S10: 142916.09 | T10: 35591.6 | U10: 135433.07 | V10: 120640.94 | W10: 127700.11 | X10: 128642.76 | Y10: 98852.59 | Z10: 109502.81 | AA10: 73381.72 | AB10: -16858.28 | AC10: 0 | AD10: 0 | AE10: 0 | AF10: 0 | AG10: 0 | AH10: 0 | AI10: 0 | AJ10: 0 | AK10: 0 | AL10: 0 | AM10: 6712.67 | AN10: 7623.82 | AO10: 7291.58 | AP10: 7615.75 | AQ10: 8659.43 | AR10: 6395.12 | AS10: 10207.47 | AT10: 15152.12 | AU10: 10678.27 | AV10: 7306.9 | AW10: 7087.91 | AX10: 9724.83 | AY10: 131837.74 | AZ10: 129710.58 | BA10: 129253.81 | BB10: 121473.48 | BC10: 124947.41 | BD10: 125444.06 | BE10: 113704.89 | BF10: 111983.64 | BG10: 117963.67 | BH10: 115286.56 | BI10: 112915 | BJ10: 123277.31 | BK10: 128811.39 | BL10: 139779.34 | BM10: 138272.42 | BN10: 143404.34 | BO10: 145593.28 | BP10: 138441.8 | BQ10: 137428.01 | BR10: 131714.11 | BS10: 133762.5 | BT10: 130696.8 | BU10: 117069.15 | BV10: 130390.11
A11: 412 | B11: SG&A: Insurance | C11: 369.27 | D11: 369.27 | E11: 369.27 | F11: 369.27 | G11: 369.27 | H11: 369.27 | I11: 369.27 | J11: 369.27 | K11: 369.27 | L11: 369.27 | M11: 369.27 | N11: 369.27 | O11: 3238.31 | P11: 3238.31 | Q11: 2203.13 | R11: 2893.25 | S11: -1142.35 | T11: 2027.45 | U11: 1944.57 | V11: 3344.97 | W11: 4206.1 | X11: 4206.1 | Y11: 4023.88 | Z11: 4114.99 | AA11: 1490.03 | AB11: 0 | AC11: 0 | AD11: 0 | AE11: 0 | AF11: 0 | AG11: 0 | AH11: 0 | AI11: 0 | AJ11: 0 | AK11: 0 | AL11: 0 | AM11: 25.03 | AN11: 25.03 | AO11: 25.03 | AP11: 25.03 | AQ11: 25.03 | AR11: 25.03 | AS11: 24.21 | AT11: 24.21 | AU11: 25.03 | AV11: 25.03 | AW11: 25.03 | AX11: 25.03 | AY11: 2069 | AZ11: 2069 | BA11: 2069 | BB11: 2069 | BC11: 2069 | BD11: 2069 | BE11: 2069 | BF11: 2069 | BG11: 2069 | BH11: 2069 | BI11: 2069 | BJ11: 2069 | BK11: 3138.05 | BL11: 3138.05 | BM11: 3138.05 | BN11: 3138.05 | BO11: 3138.05 | BP11: 3138.05 | BQ11: 3138.05 | BR11: 3138.05 | BS11: 3138.05 | BT11: 3138.05 | BU11: 3138.05 | BV11: 3138.05
A12: 415 | B12: SG&A: Management Fees | C12: 0 | D12: 0 | E12: 0 | F12: 0 | G12: 306714 | H12: 69149 | I12: 80135 | J12: 62716 | K12: 68219 | L12: 55681 | M12: 61176 | N12: 70631 | O12: 0 | P12: 0 | Q12: 0 | R12: 0 | S12: 0 | T12: 0 | U12: 0 | V12: 0 | W12: 0 | X12: 0 | Y12: 0 | Z12: 0 | AA12: 0 | AB12: 0 | AC12: 0 | AD12: 0 | AE12: 0 | AF12: 0 | AG12: 0 | AH12: 0 | AI12: 0 | AJ12: 0 | AK12: 0 | AL12: 0 | AM12: 0 | AN12: 0 | AO12: 0 | AP12: 0 | AQ12: 0 | AR12: 0 | AS12: 0 | AT12: 0 | AU12: 0 | AV12: 0 | AW12: 0 | AX12: 0 | AY12: 0 | AZ12: 0 | BA12: 0 | BB12: 0 | BC12: 0 | BD12: 0 | BE12: 0 | BF12: 0 | BG12: 0 | BH12: 0 | BI12: 0 | BJ12: 0 | BK12: 0 | BL12: 0 | BM12: 0 | BN12: 0 | BO12: 0 | BP12: 0 | BQ12: 0 | BR12: 0 | BS12: 0 | BT12: 0 | BU12: 0 | BV12: 0
A13: 416 | B13: SG&A: Occupancy Costs | C13: 4134.33 | D13: 4134.33 | E13: 4134.33 | F13: 4134.33 | G13: 4134.33 | H13: 4134.33 | I13: 4134.33 | J13: 4134.33 | K13: 4674.59 | L13: 4178.39 | M13: 4178.39 | N13: 4178.39 | O13: 10465.74 | P13: 10431.79 | Q13: 10088.79 | R13: 9483.06 | S13: 9931.79 | T13: 9931.79 | U13: 9931.79 | V13: 9931.79 | W13: 9931.79 | X13: 15120.53 | Y13: 11627.33 | Z13: 11627.33 | AA13: -73924.55 | AB13: 4127.33 | AC13: 4127.33 | AD13: 4127.33 | AE13: 4127.33 | AF13: 4127.33 | AG13: 0 | AH13: 0 | AI13: 0 | AJ13: 0 | AK13: 0 | AL13: 0 | AM13: 4073.33 | AN13: 4073.33 | AO13: 4073.33 | AP13: 4073.33 | AQ13: 4073.33 | AR13: 4073.33 | AS13: 4073.33 | AT13: 4510.36 | AU13: 4038.33 | AV13: 4073.33 | AW13: 4073.33 | AX13: 4073.33 | AY13: 9549 | AZ13: 9549 | BA13: 9549 | BB13: 9549 | BC13: 9549 | BD13: 9549 | BE13: 9549 | BF13: 11577 | BG13: 11823 | BH13: 11576 | BI13: 11083 | BJ13: 11823 | BK13: 11928.39 | BL13: 11928.39 | BM13: 11928.39 | BN13: 11928.39 | BO13: 11928.39 | BP13: 11928.39 | BQ13: 11928.39 | BR13: 12761.72 | BS13: 12761.72 | BT13: 12761.72 | BU13: 12761.72 | BV13: 12761.72
... A29: 901 | B29: Other Expenses | C29: 0 | D29: 0 | E29: 0 | F29: 0 | G29: 0 | H29: 0 | I29: 0 | J29: 0 | K29: 0 | L29: 0 | M29: 0 | N29: 0 | O29: 0 | P29: 0 | Q29: 0 | R29: 0 | S29: 0 | T29: 0 | U29: 0 | V29: 0 | W29: 0 | X29: 0 | Y29: 0 | Z29: 0 | AA29: 0 | AB29: 0 | AC29: 0 | AD29: 0 | AE29: 0 | AF29: 0 | AG29: 0 | AH29: 0 | AI29: 0 | AJ29: 0 | AK29: 0 | AL29: 0 | AM29: 0 | AN29: 0 | AO29: 0 | AP29: 0 | AQ29: 0 | AR29: 0 | AS29: 0 | AT29: 0 | AU29: 0 | AV29: 0 | AW29: 0 | AX29: 0 | AY29: 0 | AZ29: 0 | BA29: 0 | BB29: 0 | BC29: 0 | BD29: 0 | BE29: 0 | BF29: 0 | BG29: 0 | BH29: 0 | BI29: 0 | BJ29: 0 | BK29: 0 | BL29: 0 | BM29: 0 | BN29: 0 | BO29: 0 | BP29: 0 | BQ29: 0 | BR29: 0 | BS29: 0 | BT29: 0 | BU29: 0 | BV29: 0
C31: =SUMPRODUCT(CISS[[LY01]:[LY02]]) -> 4458646.5

Sheet REFERENCE
A1: MONTH | B1: CON | C1: QUA | F1: YEAR | G1: CODE | J1: YEAR | K1: MONTH | L1: CON | M1: INDEX
A2: JANUARY | B2: 10 | C2: 10 | F2: LAST YEAR | G2: LY | J2: LAST YEAR | K2: JANUARY | L2: LY10 | M2: 1
A3: FEBRUARY | B3: 11 | C3: 10 | F3: THIS YEAR | G3: TY | J3: LAST YEAR | K3: FEBRUARY | L3: LY11 | M3: 2
A4: MARCH | B4: 12 | C4: 10 | F4: NEXT YEAR | G4: NY | J4: LAST YEAR | K4: MARCH | L4: LY12 | M4: 3
A5: APRIL | B5: 01 | C5: 01 | J5: LAST YEAR | K5: APRIL | L5: LY01 | M5: 4
A6: MAY | B6: 02 | C6: 01 | J6: LAST YEAR | K6: MAY | L6: LY02 | M6: 5
A7: JUNE | B7: 03 | C7: 01 | F7: YEAR | G7: CODE | J7: LAST YEAR | K7: JUNE | L7: LY03 | M7: 6
A8: JULY | B8: 04 | C8: 04 | F8: LAST YEAR | G8: LY | J8: LAST YEAR | K8: JULY | L8: LY04 | M8: 7
A9: AUGUST | B9: 05 | C9: 04 | F9: THIS YEAR | G9: TY | J9: LAST YEAR | K9: AUGUST | L9: LY05 | M9: 8
A10: SEPTEMBER | B10: 06 | C10: 04 | F10: NEXT YEAR | G10: NY | J10: LAST YEAR | K10: SEPTEMBER | L10: LY06 | M10: 9
A11: OCTOBER | B11: 07 | C11: 07 | J11: LAST YEAR | K11: OCTOBER | L11: LY07 | M11: 10
A12: NOVEMBER | B12: 08 | C12: 07 | J12: LAST YEAR | K12: NOVEMBER | L12: LY08 | M12: 11
A13: DECEMBER | B13: 09 | C13: 07 | J13: LAST YEAR | K13: DECEMBER | L13: LY09 | M13: 12
J14: THIS YEAR | K14: JANUARY | L14: TY10 | M14: 13
J15: THIS YEAR | K15: FEBRUARY | L15: TY11 | M15: 14
J16: THIS YEAR | K16: MARCH | L16: TY12 | M16: 15
J17: THIS YEAR | K17: APRIL | L17: TY01 | M17: 16
J18: THIS YEAR | K18: MAY | L18: TY02 | M18: 17
J19: THIS YEAR | K19: JUNE | L19: TY03 | M19: 18
J20: THIS YEAR | K20: JULY | L20: TY04 | M20: 19
J21: THIS YEAR | K21: AUGUST | L21: TY05 | M21: 20
J22: THIS YEAR | K22: SEPTEMBER | L22: TY06 | M22: 21
J23: THIS YEAR | K23: OCTOBER | L23: TY07 | M23: 22
J24: THIS YEAR | K24: NOVEMBER | L24: TY08 | M24: 23
J25: THIS YEAR | K25: DECEMBER | L25: TY09 | M25: 24
... J37: NEXT YEAR | K37: DECEMBER | L37: NY09 | M37: 36

Sheet SPECIAL ACCOUNTS
A1: DIV | B1: SubGroup | C1: SubGroup_Name | D1: ACCT_NO | E1: DEP | F1: ACCT | G1: CHANNEL | H1: BRAND | I1: NAME | J1: LY01 | K1: LY02 | L1: LY03 | M1: LY04 | N1: LY05 | O1: LY06 | P1: LY07 | Q1: LY08 | R1: LY09 | S1: LY10 | T1: LY11 | U1: LY12 | V1: TY01 | W1: TY02 | X1: TY03 | Y1: TY04 | Z1: TY05 | AA1: TY06 | AB1: TY07 | AC1: TY08 | AD1: TY09 | AE1: TY10 | AF1: TY11 | AG1: TY12 | AH1: NY01 | AI1: NY02 | AJ1: NY03 | AK1: NY04 | AL1: NY05 | AM1: NY06 | AN1: NY07 | AO1: NY08 | AP1: NY09 | AQ1: NY10 | AR1: NY11 | AS1: NY12 | AT1: BLY01 | AU1: BLY02 | AV1: BLY03 | AW1: BLY04 | AX1: BLY05 | AY1: BLY06 | AZ1: BLY07 | BA1: BLY08 | BB1: BLY09 | BC1: BLY10 | BD1: BLY11 | BE1: BLY12 | BF1: BTY01 | BG1: BTY02 | BH1: BTY03 | BI1: BTY04 | BJ1: BTY05 | BK1: BTY06 | BL1: BTY07 | BM1: BTY08 | BN1: BTY09 | BO1: BTY10 | BP1: BTY11 | BQ1: BTY12 | BR1: BNY01 | BS1: BNY02 | BT1: BNY03 | BU1: BNY04 | BV1: BNY05 | BW1: BNY06 | BX1: BNY07 | BY1: BNY08 | BZ1: BNY09 | CA1: BNY10 | CB1: BNY11 | CC1: BNY12
A2: DEST | B2: 401 | C2: SG&A: Advertising | D2: MKT71550 | F2: 71550 | J2: 0 | K2: 0 | L2: 266 | M2: 0 | N2: 0 | O2: 0 | P2: 0 | Q2: 0 | R2: 0 | S2: 0 | T2: 0 | U2: 0 | V2: 0 | W2: 0 | X2: 0 | Y2: 0 | Z2: 0 | AA2: 0 | AB2: 0 | AC2: 0 | AD2: 0 | AE2: 0 | AF2: 0 | AG2: 0 | AH2: 0 | AI2: 0 | AJ2: 0 | AK2: 0 | AL2: 0 | AM2: 0 | AN2: 0 | AO2: 0 | AP2: 0 | AQ2: 0 | AR2: 0 | AS2: 0 | AT2: 0 | AU2: 0 | AV2: 0 | AW2: 0 | AX2: 0 | AY2: 0 | AZ2: 0 | BA2: 0 | BB2: 0 | BC2: 0 | BD2: 0 | BE2: 0 | BF2: 0 | BG2: 0 | BH2: 266 | BI2: 0 | BJ2: 0 | BK2: 0 | BL2: 0 | BM2: 0 | BN2: 0 | BO2: 0 | BP2: 0 | BQ2: 0 | BR2: 0 | BS2: 0 | BT2: 0 | BU2: 0 | BV2: 0 | BW2: 0 | BX2: 0 | BY2: 0 | BZ2: 0 | CA2: 0 | CB2: 0 | CC2: 0
A3: DEST | B3: 401 | C3: SG&A: Advertising | D3: MKT71550INHONO | F3: 71550 | J3: 0 | K3: 0 | L3: 0 | M3: 0 | N3: 0 | O3: 0 | P3: 0 | Q3: 0 | R3: 0 | S3: 0 | T3: 0 | U3: 0 | V3: 0 | W3: 0 | X3: 0 | Y3: 0 | Z3: 0 | AA3: 0 | AB3: 0 | AC3: 0 | AD3: 0 | AE3: 0 | AF3: 0 | AG3: 0 | AH3: 0 | AI3: 0 | AJ3: 0 | AK3: 0 | AL3: 0 | AM3: 0 | AN3: 0 | AO3: 0 | AP3: 0 | AQ3: 0 | AR3: 0 | AS3: 0 | AT3: 0 | AU3: 0 | AV3: 0 | AW3: 0 | AX3: 0 | AY3: 0 | AZ3: 0 | BA3: 0 | BB3: 0 | BC3: 0 | BD3: 0 | BE3: 0 | BF3: 0 | BG3: 0 | BH3: 0 | BI3: 0 | BJ3: 0 | BK3: 0 | BL3: 0 | BM3: 0 | BN3: 0 | BO3: 0 | BP3: 0 | BQ3: 0 | BR3: 0 | BS3: 0 | BT3: 0 | BU3: 0 | BV3: 0 | BW3: 0 | BX3: 0 | BY3: 0 | BZ3: 0 | CA3: 0 | CB3: 0 | CC3: 0
A4: DEST | B4: 401 | C4: SG&A: Advertising | D4: MKT71550ROHONO | F4: 71550 | J4: 0 | K4: 0 | L4: 0 | M4: 0 | N4: 0 | O4: 0 | P4: 0 | Q4: 0 | R4: 0 | S4: 0 | T4: 0 | U4: 0 | V4: 0 | W4: 0 | X4: 0 | Y4: 32 | Z4: 10.5 | AA4: 73.5 | AB4: 0 | AC4: 0 | AD4: 0 | AE4: 0 | AF4: 0 | AG4: 0 | AH4: 0 | AI4: 0 | AJ4: 0 | AK4: 0 | AL4: 0 | AM4: 0 | AN4: 0 | AO4: 0 | AP4: 0 | AQ4: 0 | AR4: 0 | AS4: 0 | AT4: 0 | AU4: 0 | AV4: 0 | AW4: 0 | AX4: 0 | AY4: 0 | AZ4: 0 | BA4: 0 | BB4: 0 | BC4: 0 | BD4: 0 | BE4: 0 | BF4: 0 | BG4: 0 | BH4: 0 | BI4: 0 | BJ4: 0 | BK4: 0 | BL4: 0 | BM4: 0 | BN4: 0 | BO4: 0 | BP4: 0 | BQ4: 0 | BR4: 0 | BS4: 0 | BT4: 0 | BU4: 32 | BV4: 10.5 | BW4: 73.5 | BX4: 0 | BY4: 0 | BZ4: 0 | CA4: 0 | CB4: 0 | CC4: 0
A5: 000 | B5: 401 | C5: SG&A: Advertising | D5: MKT71550 | F5: 71550 | J5: 0 | K5: 0 | L5: 1643.09 | M5: 0 | N5: 0 | O5: 200.94 | P5: 831.7 | Q5: 0 | R5: 0 | S5: 0 | T5: 0 | U5: 1042.05 | V5: 0 | W5: 0 | X5: 0 | Y5: 49.19 | Z5: 78.21 | AA5: 0 | AB5: 0 | AC5: 0 | AD5: 0 | AE5: 14.24 | AF5: 27.5 | AG5: 188.19 | AH5: 0 | AI5: 0 | AJ5: 0 | AK5: 0 | AL5: 0 | AM5: 0 | AN5: 0 | AO5: 0 | AP5: 0 | AQ5: 0 | AR5: 0 | AS5: 0 | AT5: 0 | AU5: 0 | AV5: 0 | AW5: 0 | AX5: 0 | AY5: 0 | AZ5: 0 | BA5: 0 | BB5: 0 | BC5: 0 | BD5: 0 | BE5: 0 | BF5: 0 | BG5: 0 | BH5: 0 | BI5: 0 | BJ5: 0 | BK5: 0 | BL5: 0 | BM5: 0 | BN5: 0 | BO5: 0 | BP5: 0 | BQ5: 0 | BR5: 0 | BS5: 0 | BT5: 0 | BU5: 49.19 | BV5: 78.21 | BW5: 0 | BX5: 0 | BY5: 0 | BZ5: 0 | CA5: 0 | CB5: 0 | CC5: 1042
A6: NC | B6: 401 | C6: SG&A: Advertising | D6: MKT71550 | F6: 71550 | J6: 0 | K6: 0 | L6: 1643.09 | M6: 0 | N6: 0 | O6: 200.94 | P6: 831.7 | Q6: 0 | R6: 0 | S6: 0 | T6: 0 | U6: 1042.05 | V6: 0 | W6: 0 | X6: 0 | Y6: 49.19 | Z6: 78.21 | AA6: 0 | AB6: 0 | AC6: 0 | AD6: 0 | AE6: 14.24 | AF6: 27.5 | AG6: 188.19 | AH6: 0 | AI6: 0 | AJ6: 0 | AK6: 0 | AL6: 0 | AM6: 0 | AN6: 0 | AO6: 0 | AP6: 0 | AQ6: 0 | AR6: 0 | AS6: 0 | AT6: 0 | AU6: 0 | AV6: 0 | AW6: 0 | AX6: 0 | AY6: 0 | AZ6: 0 | BA6: 0 | BB6: 0 | BC6: 0 | BD6: 0 | BE6: 0 | BF6: 0 | BG6: 0 | BH6: 1643 | BI6: 0 | BJ6: 0 | BK6: 201 | BL6: 832 | BM6: 0 | BN6: 0 | BO6: 0 | BP6: 0 | BQ6: 1042 | BR6: 0 | BS6: 0 | BT6: 0 | BU6: 49.19 | BV6: 78.21 | BW6: 0 | BX6: 0 | BY6: 0 | BZ6: 0 | CA6: 0 | CB6: 0 | CC6: 1042
A7: 000 | B7: 401 | C7: SG&A: Advertising | D7: MKT71550ABHONO | F7: 71550 | J7: 0 | K7: 0 | L7: 0 | M7: 0 | N7: 0 | O7: 0 | P7: 0 | Q7: 0 | R7: 0 | S7: 0 | T7: 0 | U7: 2250 | V7: 0 | W7: 0 | X7: 0 | Y7: 0 | Z7: 0 | AA7: 0 | AB7: 0 | AC7: 0 | AD7: 0 | AE7: 0 | AF7: 0 | AG7: 0 | AH7: 0 | AI7: 0 | AJ7: 0 | AK7: 0 | AL7: 0 | AM7: 0 | AN7: 0 | AO7: 0 | AP7: 0 | AQ7: 0 | AR7: 0 | AS7: 0 | AT7: 0 | AU7: 0 | AV7: 0 | AW7: 0 | AX7: 0 | AY7: 0 | AZ7: 0 | BA7: 0 | BB7: 0 | BC7: 0 | BD7: 0 | BE7: 0 | BF7: 0 | BG7: 0 | BH7: 0 | BI7: 0 | BJ7: 0 | BK7: 0 | BL7: 0 | BM7: 0 | BN7: 0 | BO7: 0 | BP7: 0 | BQ7: 0 | BR7: 0 | BS7: 0 | BT7: 0 | BU7: 0 | BV7: 0 | BW7: 0 | BX7: 0 | BY7: 0 | BZ7: 0 | CA7: 0 | CB7: 0 | CC7: 0
A8: NC | B8: 401 | C8: SG&A: Advertising | D8: MKT71550ABHONO | F8: 71550 | J8: 0 | K8: 0 | L8: 0 | M8: 0 | N8: 0 | O8: 0 | P8: 0 | Q8: 0 | R8: 0 | S8: 0 | T8: 0 | U8: 2250 | V8: 0 | W8: 0 | X8: 0 | Y8: 0 | Z8: 0 | AA8: 0 | AB8: 0 | AC8: 0 | AD8: 0 | AE8: 0 | AF8: 0 | AG8: 0 | AH8: 0 | AI8: 0 | AJ8: 0 | AK8: 0 | AL8: 0 | AM8: 0 | AN8: 0 | AO8: 0 | AP8: 0 | AQ8: 0 | AR8: 0 | AS8: 0 | AT8: 0 | AU8: 0 | AV8: 0 | AW8: 0 | AX8: 0 | AY8: 0 | AZ8: 0 | BA8: 0 | BB8: 0 | BC8: 0 | BD8: 0 | BE8: 0 | BF8: 0 | BG8: 0 | BH8: 0 | BI8: 0 | BJ8: 0 | BK8: 0 | BL8: 0 | BM8: 0 | BN8: 0 | BO8: 0 | BP8: 0 | BQ8: 0 | BR8: 0 | BS8: 0 | BT8: 0 | BU8: 0 | BV8: 0 | BW8: 0 | BX8: 0 | BY8: 0 | BZ8: 0 | CA8: 0 | CB8: 0 | CC8: 0
A9: 000 | B9: 401 | C9: SG&A: Advertising | D9: MKT71550AGHONO | F9: 71550 | J9: 0 | K9: 0 | L9: 0 | M9: 0 | N9: 0 | O9: 0 | P9: 0 | Q9: 0 | R9: 0 | S9: 0 | T9: 0 | U9: 131 | V9: 0 | W9: 30 | X9: 36 | Y9: 0 | Z9: 45 | AA9: 111 | AB9: 0 | AC9: 0 | AD9: 0 | AE9: -45 | AF9: 0 | AG9: 0 | AH9: 0 | AI9: 0 | AJ9: 0 | AK9: 0 | AL9: 0 | AM9: 0 | AN9: 0 | AO9: 0 | AP9: 0 | AQ9: 0 | AR9: 0 | AS9: 0 | AT9: 0 | AU9: 0 | AV9: 0 | AW9: 0 | AX9: 0 | AY9: 0 | AZ9: 0 | BA9: 0 | BB9: 0 | BC9: 0 | BD9: 0 | BE9: 0 | BF9: 0 | BG9: 0 | BH9: 0 | BI9: 0 | BJ9: 0 | BK9: 0 | BL9: 0 | BM9: 0 | BN9: 0 | BO9: 0 | BP9: 0 | BQ9: 0 | BR9: 17.83 | BS9: 31.21 | BT9: 92.68 | BU9: 89.17 | BV9: 78.36 | BW9: 80.25 | BX9: 70.96 | BY9: 34.41 | BZ9: 27.53 | CA9: 34.41 | CB9: 93.04 | CC9: 35.04
A10: NC | B10: 401 | C10: SG&A: Advertising | D10: MKT71550AGHONO | F10: 71550 | J10: 0 | K10: 0 | L10: 0 | M10: 0 | N10: 0 | O10: 0 | P10: 0 | Q10: 0 | R10: 0 | S10: 0 | T10: 0 | U10: 131 | V10: 0 | W10: 30 | X10: 36 | Y10: 0 | Z10: 45 | AA10: 111 | AB10: 0 | AC10: 0 | AD10: 0 | AE10: -45 | AF10: 0 | AG10: 0 | AH10: 0 | AI10: 0 | AJ10: 0 | AK10: 0 | AL10: 0 | AM10: 0 | AN10: 0 | AO10: 0 | AP10: 0 | AQ10: 0 | AR10: 0 | AS10: 0 | AT10: 0 | AU10: 0 | AV10: 0 | AW10: 0 | AX10: 0 | AY10: 0 | AZ10: 0 | BA10: 0 | BB10: 0 | BC10: 0 | BD10: 0 | BE10: 0 | BF10: 0 | BG10: 0 | BH10: 0 | BI10: 0 | BJ10: 0 | BK10: 0 | BL10: 0 | BM10: 0 | BN10: 0 | BO10: 0 | BP10: 0 | BQ10: 0 | BR10: 17.83 | BS10: 31.21 | BT10: 92.68 | BU10: 89.17 | BV10: 78.36 | BW10: 80.25 | BX10: 70.96 | BY10: 34.41 | BZ10: 27.53 | CA10: 34.41 | CB10: 93.04 | CC10: 35.04
A11: 000 | B11: 401 | C11: SG&A: Advertising | D11: MKT71550DUHONO | F11: 71550 | J11: 0 | K11: 0 | L11: 0 | M11: 0 | N11: 0 | O11: 0 | P11: 0 | Q11: 0 | R11: 0 | S11: 0 | T11: 0 | U11: 0 | V11: 0 | W11: 0 | X11: 12 | Y11: 0 | Z11: 0 | AA11: 0 | AB11: 0 | AC11: 0 | AD11: 0 | AE11: 0 | AF11: 0 | AG11: 0 | AH11: 0 | AI11: 0 | AJ11: 0 | AK11: 0 | AL11: 0 | AM11: 0 | AN11: 0 | AO11: 0 | AP11: 0 | AQ11: 0 | AR11: 0 | AS11: 0 | AT11: 0 | AU11: 0 | AV11: 0 | AW11: 0 | AX11: 0 | AY11: 0 | AZ11: 0 | BA11: 0 | BB11: 0 | BC11: 0 | BD11: 0 | BE11: 0 | BF11: 0 | BG11: 0 | BH11: 0 | BI11: 0 | BJ11: 0 | BK11: 0 | BL11: 0 | BM11: 0 | BN11: 0 | BO11: 0 | BP11: 0 | BQ11: 0 | BR11: 0 | BS11: 0 | BT11: 0 | BU11: 0 | BV11: 0 | BW11: 0 | BX11: 0 | BY11: 0 | BZ11: 0 | CA11: 0 | CB11: 0 | CC11: 0
A12: NC | B12: 401 | C12: SG&A: Advertising | D12: MKT71550DUHONO | F12: 71550 | J12: 0 | K12: 0 | L12: 0 | M12: 0 | N12: 0 | O12: 0 | P12: 0 | Q12: 0 | R12: 0 | S12: 0 | T12: 0 | U12: 0 | V12: 0 | W12: 0 | X12: 12 | Y12: 0 | Z12: 0 | AA12: 0 | AB12: 0 | AC12: 0 | AD12: 0 | AE12: 0 | AF12: 0 | AG12: 0 | AH12: 0 | AI12: 0 | AJ12: 0 | AK12: 0 | AL12: 0 | AM12: 0 | AN12: 0 | AO12: 0 | AP12: 0 | AQ12: 0 | AR12: 0 | AS12: 0 | AT12: 0 | AU12: 0 | AV12: 0 | AW12: 0 | AX12: 0 | AY12: 0 | AZ12: 0 | BA12: 0 | BB12: 0 | BC12: 0 | BD12: 0 | BE12: 0 | BF12: 0 | BG12: 0 | BH12: 0 | BI12: 0 | BJ12: 0 | BK12: 0 | BL12: 0 | BM12: 0 | BN12: 0 | BO12: 0 | BP12: 0 | BQ12: 0 | BR12: 0 | BS12: 0 | BT12: 0 | BU12: 0 | BV12: 0 | BW12: 0 | BX12: 0 | BY12: 0 | BZ12: 0 | CA12: 0 | CB12: 0 | CC12: 0
A13: 000 | B13: 401 | C13: SG&A: Advertising | D13: MKT71550EXHONO | F13: 71550 | J13: 0 | K13: 0 | L13: 0 | M13: 0 | N13: 0 | O13: 0 | P13: 0 | Q13: 0 | R13: 0 | S13: 0 | T13: 0 | U13: 396 | V13: 0 | W13: 0 | X13: 0 | Y13: 0 | Z13: 0 | AA13: 0 | AB13: 0 | AC13: 0 | AD13: 0 | AE13: 0 | AF13: 0 | AG13: 0 | AH13: 0 | AI13: 0 | AJ13: 0 | AK13: 0 | AL13: 0 | AM13: 0 | AN13: 0 | AO13: 0 | AP13: 0 | AQ13: 0 | AR13: 0 | AS13: 0 | AT13: 0 | AU13: 0 | AV13: 0 | AW13: 0 | AX13: 0 | AY13: 0 | AZ13: 0 | BA13: 0 | BB13: 0 | BC13: 0 | BD13: 0 | BE13: 0 | BF13: 0 | BG13: 0 | BH13: 0 | BI13: 0 | BJ13: 0 | BK13: 0 | BL13: 0 | BM13: 0 | BN13: 0 | BO13: 0 | BP13: 0 | BQ13: 0 | BR13: 0 | BS13: 0 | BT13: 0 | BU13: 0 | BV13: 0 | BW13: 0 | BX13: 0 | BY13: 0 | BZ13: 0 | CA13: 0 | CB13: 0 | CC13: 0
... A45: DS | B45: 416 | C45: SG&A: Occupancy Costs | D45: EXE71470 | F45: 71470 | J45: 0 | K45: 0 | L45: 0 | M45: 0 | N45: 0 | O45: 0 | P45: 0 | Q45: 0 | R45: 0 | S45: 0 | T45: 0 | U45: 0 | V45: 5753.4 | W45: 5753.4 | X45: 5753.4 | Y45: 5753.4 | Z45: 5753.4 | AA45: 5753.4 | AB45: 5753.4 | AC45: 5753.4 | AD45: 5753.4 | AE45: 10993.2 | AF45: 7500 | AG45: 7500 | AH45: -77773.8 | AI45: 0 | AJ45: 0 | AK45: 0 | AL45: 0 | AM45: 0 | AN45: 0 | AO45: 0 | AP45: 0 | AQ45: 0 | AR45: 0 | AS45: 0 | AT45: 0 | AU45: 0 | AV45: 0 | AW45: 0 | AX45: 0 | AY45: 0 | AZ45: 0 | BA45: 0 | BB45: 0 | BC45: 0 | BD45: 0 | BE45: 0 | BF45: 5370 | BG45: 5370 | BH45: 5370 | BI45: 5370 | BJ45: 5370 | BK45: 5370 | BL45: 5370 | BM45: 7398 | BN45: 7644 | BO45: 7397 | BP45: 6904 | BQ45: 7644 | BR45: 7500 | BS45: 7500 | BT45: 7500 | BU45: 7500 | BV45: 7500 | BW45: 7500 | BX45: 7500 | BY45: 8333.33 | BZ45: 8333.33 | CA45: 8333.33 | CB45: 8333.33 | CC45: 8333.33

Sheet SUBGOUP BAL WITH ACCT
A1: SUBGROUP | B1: (Multiple Items)
A2: SubGroup_Name | B2: (All)
A3: ACCT_NO_3 | B3: (All)
A4: ACCT_NO | B4: (All)
A5: NAME | B5: (All)
A6: GLGROUP | B6: (All) | S6: =SUM(G6:R6) -> 0
S7: =SUM(G7:R7) -> 0
C8: Values | S8: =SUM(G8:R8) -> 0
A9: ACCT_NO_4 | B9: DIV | C9: Sum of TY01 | D9: Sum of TY02 | E9: Sum of TY03 | F9: Sum of TY04 | G9: Sum of TY05 | H9: Sum of TY06 | I9: Sum of TY07 | J9: Sum of TY08 | K9: Sum of TY09 | L9: Sum of TY10 | M9: Sum of TY11 | N9: Sum of TY12 | S9: =SUM(G9:R9) -> 0
C10: 7616.19 | D10: 6469.5 | E10: 168347.66 | F10: 18473.44 | G10: 218507.03 | H10: 136501.16 | I10: 77792.57 | J10: 211139.02 | K10: -29538.61 | L10: 245408.63 | M10: 114116.38 | N10: 141675.46 | S10: =SUM(G10:R10) -> 1115601.6
B11: DEST | C11: 98.69 | D11: 700.09 | E11: 709.44 | F11: 744.72 | G11: 544.24 | H11: 576.58 | I11: 891.13 | J11: 1154.95 | K11: 2408.66 | L11: 881.03 | M11: 1053.46 | N11: 1731.41 | S11: =SUM(G11:R11) -> 9241.46
B12: DS | C12: 135.39 | D12: 186.04 | E12: 393.02 | F12: 608.1 | G12: 633.54 | H12: 41969.99 | I12: 56718.36 | J12: -122.03 | K12: 383.34 | L12: 78.67 | M12: 2754.37 | N12: -817.53 | S12: =SUM(G12:R12) -> 101598.71
B13: HO | C13: 0 | D13: 0 | E13: 0 | F13: 0 | G13: 0 | H13: 0 | I13: 0 | J13: 0 | K13: 0 | L13: 0 | M13: 0 | N13: 0 | S13: =SUM(G13:R13) -> 0
B14: NC | C14: 7382.11 | D14: 5583.37 | E14: 167245.2 | F14: 17120.62 | G14: 217329.25 | H14: 93954.59 | I14: 20183.08 | J14: 210106.1 | K14: -32330.61 | L14: 244448.93 | M14: 110308.55 | N14: 140761.58 | S14: =SUM(G14:R14) -> 1004761.5
A15: 20BE | C15: 248974.83 | D15: 295151.96 | E15: 199983.3 | F15: 265177.39 | G15: 238561.67 | H15: 288620.19 | I15: 222494.65 | J15: 269458.18 | K15: 192424.47 | L15: 236629.11 | M15: 148721.04 | N15: 120423.96 | S15: =SUM(G15:R15) -> 1717333.3
A16: BENC | C16: 103944.2 | D16: 129920.43 | E16: 128261.08 | F16: 128651.73 | G16: 112155.51 | H16: 132497.47 | I16: 129190.31 | J16: 117390.25 | K16: 154989.52 | L16: 83307.27 | M16: 92104.7 | N16: 98550.6 | S16: =SUM(G16:R16) -> 920185.63
A17: CAND | C17: 31667.37 | D17: 25048.23 | E17: 13731.05 | F17: 16030.59 | G17: 3483.67 | H17: 45972.69 | I17: 16915.98 | J17: 28280.72 | K17: 8381.82 | L17: 9794.84 | M17: 39197.43 | N17: 18954.4 | S17: =SUM(G17:R17) -> 170981.55
A18: CELI | C18: 0 | D18: 0 | E18: 124.53 | F18: 28431.4 | G18: 1859.3 | H18: 338.43 | I18: 27662.47 | J18: 125.22 | K18: 125.22 | L18: 3767.12 | M18: 37.2 | N18: 298.42 | S18: =SUM(G18:R18) -> 34213.38
A19: CROO | C19: 933.81 | D19: 49.05 | E19: 96129.03 | F19: 66.08 | G19: 884 | H19: 96551 | I19: 23309.36 | J19: 1339.74 | K19: 602.34 | L19: 2535 | M19: 3335.99 | N19: 892.84 | S19: =SUM(G19:R19) -> 129450.27
A20: DANA | C20: 85440.71 | D20: 64418.26 | E20: 60781.11 | F20: 59871.32 | G20: 100808.58 | H20: 58876.27 | I20: 111439.45 | J20: 95988.54 | K20: 47637.31 | L20: 70538.19 | M20: 55511.95 | N20: 51374.73 | S20: =SUM(G20:R20) -> 592175.02
A21: DARE | C21: 0 | D21: 0 | E21: 0 | F21: 0 | G21: 0 | H21: 0 | I21: 0 | J21: 0 | K21: 0 | L21: 0 | M21: 0 | N21: 0 | S21: =SUM(G21:R21) -> 0
A22: DESO | C22: 38745.68 | D22: 192865.58 | E22: 58031.03 | F22: 84328.91 | G22: 39771.27 | H22: 49412.47 | I22: 319862.98 | J22: 65198.02 | K22: 47296.65 | L22: 37440.14 | M22: 46152.19 | N22: 31287.78 | S22: =SUM(G22:R22) -> 636421.5
A23: EAST | C23: 287001.86 | D23: 246032.86 | E23: 133590.41 | F23: 232677.66 | G23: 181073.63 | H23: 244547.41 | I23: 239162.08 | J23: 220336.25 | K23: 181997.83 | L23: 161740.93 | M23: 116462.54 | N23: 167324.68 | S23: =SUM(G23:R23) -> 1512645.4
A24: FRES | C24: 61271.38 | D24: 26191.42 | E24: 36376.08 | F24: 42910.13 | G24: 17161.23 | H24: 39207.84 | I24: 12031.1 | J24: 22656.85 | K24: 14307.73 | L24: 45169.58 | M24: 23612.89 | N24: 38697.73 | S24: =SUM(G24:R24) -> 212844.95
A25: HATT | C25: 4513.38 | D25: 2893.62 | E25: 1745.94 | F25: -2068.2 | G25: 1288.92 | H25: 2144.06 | I25: 1911.96 | J25: 833.9 | K25: 3638.71 | L25: 442.82 | M25: 1597.74 | N25: 4089.29 | S25: =SUM(G25:R25) -> 15947.4
A26: HONO | C26: 7658.18 | D26: 50318.24 | E26: 16632.49 | F26: 31489.27 | G26: 28860.24 | H26: 141087.28 | I26: 30507.44 | J26: 34341.69 | K26: 40606.38 | L26: 7045.78 | M26: 17056.1 | N26: 34453.8 | S26: =SUM(G26:R26) -> 333958.71
... A33: SUND | C33: 3424.16 | D33: 3207.35 | E33: 3711.18 | F33: 4066.97 | G33: 4337.81 | H33: 3055.44 | I33: 2561.95 | J33: 2639.82 | K33: 4022.16 | L33: 2742.86 | M33: 2341.51 | N33: 3529.54 | S33: =SUM(G33:R33) -> 25231.09
A34: TZAF | C34: 0 | D34: 0 | E34: 0 | F34: 0 | G34: 0 | H34: 0 | I34: 0 | J34: 0 | K34: 0 | L34: 49025.36 | M34: 0 | N34: 129.92
A35: Grand Total | C35: 1152515.8 | D35: 1478895.3 | E35: 1180873 | F35: 1263935 | G35: 1129263.2 | H35: 1504503.4 | I35: 1785201.7 | J35: 1294608 | K35: 896772.24 | L35: 1030221.2 | M35: 739985.95 | N35: 1033589.8

Sheet Sheet1
C1: 1 | D1: 2 | E1: 3 | F1: 4 | G1: 5 | H1: 6 | I1: 7 | J1: 8 | K1: 9 | L1: 10 | M1: 11 | N1: 12
A2: C-1000 | B2: Wine Clearing COGS | C2: 0 | D2: 0 | E2: 0 | F2: 0 | G2: -3420 | H2: 3420 | I2: 0 | J2: 0.01 | K2: -0.01 | L2: 0 | M2: 0 | N2: 0 | O2: =SUM(C2:N2) -> 0
A3: C-1010 | B3: Retail Onsite COGS | C3: 35760.82 | D3: 17405.98 | E3: 17043.2 | F3: -36.97 | G3: 23122.44 | H3: 21284.22 | I3: 20715.65 | J3: 7343.46 | K3: 28592.74 | L3: 10436.19 | M3: 13866.76 | N3: 15045.66 | O3: =SUM(C3:N3) -> 210580.15
A4: C-1020 | B4: Retail Invoiced COGS | C4: 24443.77 | D4: 19940.86 | E4: 27024.1 | F4: 4692.19 | G4: 16749.41 | H4: 18353.84 | I4: 21618.65 | J4: 23695.4 | K4: 38016.6 | L4: 21462.15 | M4: 18922.43 | N4: 15231.43 | O4: =SUM(C4:N4) -> 250150.83
A5: C-1030 | B5: Licensee COGS | C5: 96028.16 | D5: 109933.58 | E5: 114296.71 | F5: 122458.07 | G5: 105813.9 | H5: 118129.86 | I5: 118071.58 | J5: 110484.55 | K5: 137289.82 | L5: 83158.47 | M5: 82540.34 | N5: 105657.41 | O5: =SUM(C5:N5) -> 1303862.4
A6: C-1040 | B6: LCBO COGS | C6: 300020.67 | D6: 237746.8 | E6: 203752.11 | F6: 292373.22 | G6: 249584.34 | H6: 193967.81 | I6: 223837.68 | J6: 321809.6 | K6: 191027.32 | L6: 246896.08 | M6: 151518.31 | N6: 157485.98 | O6: =SUM(C6:N6) -> 2770019.9
A7: C-1045 | B7: Duty Free COGS | C7: 1525.62 | D7: 2929.57 | E7: 1428.43 | F7: 2936.09 | G7: 3370.33 | H7: 127.42 | I7: 15.44 | J7: 652.95 | K7: 1215.7 | L7: 23.84 | M7: 200.66 | N7: -9.12 | O7: =SUM(C7:N7) -> 14416.93
A8: C-1050 | B8: Export COGS | C8: 98960.61 | D8: 416806.09 | E8: 110815.64 | F8: 181517.38 | G8: 17653.54 | H8: 247568.77 | I8: 460109.67 | J8: 29079.15 | K8: 58810.28 | L8: 8775.87 | M8: 526.73 | N8: 119776.47 | O8: =SUM(C8:N8) -> 1750400.2
A9: C-1060 | B9: Extra-Provincial COGS | C9: 5985.09 | D9: 9901.64 | E9: 13543.08 | F9: 1537.32 | G9: 5698.37 | H9: 9000.72 | I9: 37875.8 | J9: 18639.13 | K9: 5915.25 | L9: 16047.64 | M9: 15295.1 | N9: 2409.13 | O9: =SUM(C9:N9) -> 141848.27
A10: C-1190 | B10: Grape Juice COGS | C10: 0 | D10: 0 | E10: 0 | F10: 0 | G10: 0 | H10: 0 | I10: 0 | J10: 0 | K10: 29815.21 | L10: 0 | M10: 0 | N10: 0 | O10: =SUM(C10:N10) -> 29815.21
A11: C-1200 | B11: Bulk Wine COGS | C11: 185.55 | D11: 0 | E11: 142200.05 | F11: 17796.33 | G11: 254136.57 | H11: 36368.13 | I11: 14284.12 | J11: 145255.58 | K11: 2214.89 | L11: 169558.59 | M11: 81979.87 | N11: 97136.52 | O11: =SUM(C11:N11) -> 961116.2
A12: C-1210 | B12: Other COGS | C12: 10323.46 | D12: -2158.04 | E12: 5318.95 | F12: -9714.22 | G12: -2382.57 | H12: 43010.34 | I12: -4184.8 | J12: 6437.61 | K12: 28739.61 | L12: 9335 | M12: 8811.69 | N12: 2950.91 | O12: =SUM(C12:N12) -> 96487.94
A13: C-1230 | C13: 0 | D13: 0 | E13: 0 | F13: 23157.5 | G13: 18916.02 | H13: 12030.34 | I13: 4857.32 | J13: 19486.32 | K13: 36818.45 | L13: 9498.68 | M13: 12273.25 | N13: 34433.6 | O13: =SUM(C13:N13) -> 171471.48
A14: C-1240 | C14: 0 | D14: 0 | E14: 0 | F14: 0 | G14: 0 | H14: 0 | I14: 0 | J14: 0 | K14: 0 | L14: 0 | M14: 0 | N14: 0 | O14: =SUM(C14:N14) -> 0
A15: C-1250 | C15: 0 | D15: 0 | E15: 0 | F15: 0 | G15: 0 | H15: 0 | I15: 0 | J15: 0 | K15: 0 | L15: 0 | M15: 0 | N15: 0 | O15: =SUM(C15:N15) -> 0
A16: C-2000 | B16: Grape COGS | C16: 0 | D16: 0 | E16: 0 | F16: 0 | G16: 0 | H16: 0 | I16: 0 | J16: 0 | K16: 0 | L16: 0 | M16: 0 | N16: 0 | O16: =SUM(C16:N16) -> 0
C17: =SUM(C1:C16) -> 573234.75 | D17: =SUM(D1:D16) -> 812508.48 | E17: =SUM(E1:E16) -> 635425.27 | F17: =SUM(F1:F16) -> 636720.91 | G17: =SUM(G1:G16) -> 689247.35 | H17: =SUM(H1:H16) -> 703267.45 | I17: =SUM(I1:I16) -> 897208.11 | J17: =SUM(J1:J16) -> 682891.76 | ... O17: =SUM(O1:O16) -> 7700169.6
A22: C-1010 | C22: 35760.82 | D22: 17030.98 | E22: 16290.9 | F22: -680.49 | G22: 22349.3 | H22: 20482.34 | I22: 20076.81 | J22: 6782.91 | K22: 28286.33 | L22: 10144.85 | M22: 13570.59 | N22: 14676.85 | O22: =SUM(C22:N22) -> 204772.19
A23: C-1020 | C23: 24443.77 | D23: 19060.86 | E23: 26800.57 | F23: 4499.15 | G23: 16516.42 | H23: 18037.52 | I23: 17863.15 | J23: 23425.21 | K23: 36755.07 | L23: 18400.88 | M23: 18645.19 | N23: 14046.24 | O23: =SUM(C23:N23) -> 238494.03
A24: C-1030 | C24: 96028.16 | D24: 108963.58 | E24: 113689.98 | F24: 122092.42 | G24: 104630.78 | H24: 117302.33 | I24: 116797.03 | J24: 109493.73 | K24: 135849.72 | L24: 80901.79 | M24: 81264.99 | N24: 105900.15 | O24: =SUM(C24:N24) -> 1292914.7
A25: C-1040 | C25: 300020.67 | D25: 223326.8 | E25: 199309.25 | F25: 287326.32 | G25: 241777.13 | H25: 190286.22 | I25: 216964.74 | J25: 314830.22 | K25: 189396.34 | L25: 241375.84 | M25: 149095.03 | N25: 154877.3 | O25: =SUM(C25:N25) -> 2708585.9
A26: C-1045 | C26: 1525.62 | D26: 2929.57 | E26: 1293.47 | F26: 2896.08 | G26: 3293.91 | H26: 0.01 | I26: 0 | J26: 652.95 | K26: 1174.21 | L26: 0 | M26: 146 | N26: 0 | O26: =SUM(C26:N26) -> 13911.82
A27: C-1050 | C27: 98960.61 | D27: 415606.09 | E27: 110638.36 | F27: 181466.65 | G27: 17643.54 | H27: 247553.17 | I27: 455983.25 | J27: 29050.43 | K27: 58796.99 | L27: 8720.78 | M27: 526.73 | N27: 119775.87 | O27: =SUM(C27:N27) -> 1744722.5
A28: C-1060 | C28: 5985.09 | D28: 9351.64 | E28: 13782.65 | F28: 636.42 | G28: 5584.41 | H28: 9167.41 | I28: 37632.35 | J28: 17269.54 | K28: 5913.78 | L28: 16047.64 | M28: 14374.03 | N28: 2334.13 | O28: =SUM(C28:N28) -> 138079.09
A29: C-1200 | C29: 0 | D29: 0 | E29: 0 | F29: 0 | G29: 0 | H29: 0 | I29: 0 | J29: 0 | K29: 0 | L29: 0 | M29: 0 | N29: 0 | O29: =SUM(C29:N29) -> 0
A30: C-1210 | C30: 5892.85 | D30: 4.43 | E30: 318.95 | F30: 41.35 | G30: 0 | H30: 10.34 | I30: 0 | J30: 0 | K30: 39.87 | L30: 0 | M30: 0 | N30: 0 | O30: =SUM(C30:N30) -> 6307.79
A31: C-1230 | C31: 0 | D31: 0 | E31: 0 | F31: 23157.5 | G31: 18251.22 | H31: 9263.14 | I31: 4545.32 | J31: 18238.32 | K31: 34496.45 | L31: 9090.68 | M31: 11517.25 | N31: 32321.6 | O31: =SUM(C31:N31) -> 160881.48
A32: C-2000 | C32: 0 | D32: 0 | E32: 0 | F32: 0 | G32: 0 | H32: 0 | I32: 0 | J32: 0 | K32: 0 | L32: 0 | M32: 0 | N32: 0 | O32: =SUM(C32:N32) -> 0
A33: X-1250 | C33: 0 | D33: 0 | E33: 0 | F33: 0 | G33: 0 | H33: 0 | I33: 0 | J33: 0 | K33: 0 | L33: 0 | M33: 0 | N33: 0 | O33: =SUM(C33:N33) -> 0
... A35: C-1250 | C35: 0 | D35: 0 | E35: 0 | F35: 0 | G35: 0 | H35: 0 | I35: 0 | J35: 0 | K35: 0 | L35: 0 | M35: 0 | N35: 0 | O35: =SUM(C35:N35) -> 0
C36: =SUM(C22:C35) -> 568617.59 | D36: =SUM(D22:D35) -> 796273.95 | E36: =SUM(E22:E35) -> 482124.13 | F36: =SUM(F22:F35) -> 621435.4 | G36: =SUM(G22:G35) -> 430046.71 | H36: =SUM(H22:H35) -> 612102.48 | I36: =SUM(I22:I35) -> 869862.65 | J36: =SUM(J22:J35) -> 519743.31 | ... O36: =SUM(O22:O35) -> 6508669.4
